Workbook

Sheet Inputs
A1: Input assumptions: every row of inputs.csv and assumptions.csv (base case values)
A2: Values are copied from disney-tourism-thailand/data/appraisal. Column C is the base case used by the appraisal. Status and source are copied from the source file.
A3: File | B3: Parameter | C3: Value (base case) | D3: Low case | E3: High case | F3: Unit | G3: Status | H3: Source or basis
A4: inputs.csv | B4: capex_complex_thb_bn | C4: 300 | F4: THB bn | G4: from proposal (not verified; reported in news on 12 February 2026 and repeated later; no official statement read) | H4: data/processed/thailand_proposal.json scenario complex_total
A5: inputs.csv | B5: capex_park_high_thb_bn | C5: 200 | F5: THB bn | G5: from proposal (not verified; reported in news on 12 and 15 May 2026; no official statement read) | H5: data/processed/thailand_proposal.json scenario park_high
A6: inputs.csv | B6: capex_park_low_thb_bn | C6: 100 | F6: THB bn | G6: from proposal (not verified; lower bound of a range reported on 27 March 2026; no official statement read) | H6: data/processed/thailand_proposal.json scenario park_low
A7: inputs.csv | B7: claim_additional_visitors_million_per_year | C7: 10 | F7: million visits per year | G7: claim (reference only; reported in news on 3 February 2026 as a conditional annual figure with no base year) | H7: data/processed/thailand_proposal.json ministerial_claims
A8: inputs.csv | B8: claim_revenue_thb_bn | C8: 150 | F8: THB bn | G8: claim (reference only; reported in news on 3 February 2026 as more than THB 150 billion, conditional, with no period) | H8: data/processed/thailand_proposal.json ministerial_claims
A9: inputs.csv | B9: claim_share_of_gdp_percent_per_year | C9: 1 | F9: percent per year of GDP growth | G9: claim (reference only; reported on 3 February 2026 as an effect of 1 percent a year on the GDP growth rate, not a share of GDP) | H9: data/processed/thailand_proposal.json ministerial_claims
A10: inputs.csv | B10: discount_rate_eirr_standard | C10: 0.09 | F10: rate | G10: sourced (ADB 2017; cross-check only) | H10: ADB (2017) Guidelines for the Economic Analysis of Projects, paragraph 194 (printed page 53); DOI http://dx.doi.org/10.22617/TIM178607-2; URL https://www.adb.org/sites/default/files/institutional-document/32256/economic-analysis-projects.pdf
A11: inputs.csv | B11: discount_rate_eirr_social_sector | C11: 0.06 | F11: rate | G11: sourced (ADB 2017; social sector and environmental projects) | H11: ADB (2017) Guidelines for the Economic Analysis of Projects, paragraph 194 (printed page 53); DOI http://dx.doi.org/10.22617/TIM178607-2; URL https://www.adb.org/sites/default/files/institutional-document/32256/economic-analysis-projects.pdf
A12: inputs.csv | B12: discount_rate_social_nesdc | C12: 0.07 | F12: rate | G12: sourced (NESDC 2024; projects carried out from 2025 onward) | H12: NESDC (2024) Guide to Public Investment Project Appraisal, section 6.2.2 (PDF page 28); range in section 6.2.1 (PDF page 26); URL https://www.nesdc.go.th/wp-content/uploads/2025/05/article_20241009124821.pdf
A13: inputs.csv | B13: discount_rate_social_nesdc_pre2025 | C13: 0.12 | F13: rate | G13: reference only (applies to projects carried out before 2025) | H13: NESDC (2024) Guide to Public Investment Project Appraisal, section 6.2.2 (PDF page 28); URL https://www.nesdc.go.th/wp-content/uploads/2025/05/article_20241009124821.pdf
A14: inputs.csv | B14: conversion_factor_standard | C14: 0.7 | F14: ratio | G14: sourced (NESDC 2024) | H14: NESDC (2024) Guide to Public Investment Project Appraisal, summary of changes (PDF page 5); used when shadow prices cannot be computed; URL https://www.nesdc.go.th/wp-content/uploads/2025/05/article_20241009124821.pdf
A15: inputs.csv | B15: project_life_years | C15: 20 | F15: years | G15: team decision (confirmed by the leader on 14 October 2026): labelled assumption; not sourced; base 20 years | H15: assumptions.csv project_life_years (team recommendation; Revenue Department building depreciation of 5 percent a year; ADB ranges)
... A50: inputs.csv | B50: chonburi_foreign_arrivals_2019 | C50: 9966574 | F50: persons | G50: sourced (TAT Intelligence Center workbook, 2019 revised figure 2562R, foreign visitors to Chon Buri province; a provincial visitor count, not a count of border arrivals) | H50: https://intelligencecenter.tat.or.th/articles/9907 (TAT Intelligence Center domestic statistics workbook, 2019 revised figure 2562R)
A51: inputs.csv | B51: utapao_expansion_progress_overall_percent | F51: percent complete | G51: pending (the EECO page shows 0 percent, but its progress widget carries 16; the date label is October 2025; not used) | H51: https://www.eeco.or.th/en/u-tapao-airport-and-eastern-aviation-city/ (snapshot dated October 2025)
A52: inputs.csv | B52: utapao_expansion_opening_year | C52: 2031 | F52: calendar year | G52: sourced (trade news report of February 2026: operations targeted to begin in 2031; secondary, not an EEC primary; a five-year build from notice to proceed on 3 April 2026 gives the same year) | H52: https://www.britishaviationgroup.co.uk/?p=24880 (trade news report, February 2026)
A53: inputs.csv | B53: high_speed_rail_full_service_year_eeco | C53: 2031 | F53: calendar year | G53: sourced (EEC Office, page status October 2025) | H53: High-speed rail linking three airports, EEC Office. https://www.eeco.or.th/en/high-speed-rail-linking-three-airports/. Planned opening and key dates section (page status October 2025). Full high-speed rail service is expected to commence operations in 2031.
A54: inputs.csv | B54: high_speed_rail_full_service_year_wikipedia | C54: 2029 | F54: calendar year | G54: sourced (Wikipedia infobox, secondary; superseded: the article's own December 2025 status entry gives 2030, and the EEC Office page gives 2031, which is the value used) | H54: Don Mueang-Suvarnabhumi-U-Tapao high-speed railway, Wikipedia. https://en.wikipedia.org/wiki/Don_Mueang%E2%80%93Suvarnabhumi%E2%80%93U-Tapao_high-speed_railway. Infobox. Secondary source that conflicts with the 2031 date on the EEC Office page. The article gives 2030 in its status section.
A55: inputs.csv | B55: high_speed_rail_status_sep_2026 | F55: status text | G55: pending (text status: the project remains delayed; Nation Thailand article dated 7 September 2026; no numeric value) | H55: Uttapao and High-Speed Rail: EEC's Make-or-Break Infrastructure Bet, Nation Thailand (7 Sep 2026). https://www.nationthailand.com/business/economy/40070765. High-speed rail paragraph. The article states that the project remains delayed. Text value, not numeric.
A56: inputs.csv | B56: motorway7_utapao_extension_length_km | C56: 1.92 | F56: kilometres | G56: sourced (ADB news release, 6 June 2025) | H56: ADB news release, Thailand EEC infrastructure, 6 June 2025. https://www.adb.org/news/adb-supports-resilient-infrastructure-development-eastern-thailand. Project description paragraph. Department of Highways project financed by an ADB loan of USD 68.74 million, not converted.
A57: inputs.csv | B57: motorway7_utapao_extension_completion_year | C57: 2028 | F57: calendar year | G57: sourced (Thansettakij report dated 19 June 2025: expected completion July 2028, 36-month construction; secondary news source) | H57: https://www.thansettakij.com/economy/megaproject/630463 (report dated 19 June 2025; secondary news source)
A58: inputs.csv | B58: pattaya_map_ta_phut_motorway7_opening_year | C58: 2020 | F58: calendar year (opened August 2020) | G58: sourced (Pattaya Mail, 24 Aug 2020) | H58: Thai Prime Minister opens Pattaya-Map Ta Phut Highway, Pattaya Mail (24 Aug 2020). https://www.pattayamail.com/news/thai-prime-minister-opens-pattaya-map-ta-phut-highway-312223. Opening paragraph. Length and interchanges not stated in the fetched text.
A59: inputs.csv | B59: tat_spend_per_trip_all_nationalities_2023 | C59: 50900 | F59: THB per trip | G59: sourced (secondary: Government Public Relations Department report of the 2023 TAT survey, 50,900 THB per trip for all international tourists; the TAT primary document was not reached; per trip, not per park visit; not used by the model) | H59: Government Public Relations Department (relaying the 2023 TAT tourist spending survey of 30,054 tourists), https://thailand.prd.go.th/en/content/category/detail/id/52/iid/266973
A60: inputs.csv | B60: tat_spend_per_trip_middle_eastern_2023 | C60: 88512 | F60: THB per person per trip | G60: unconfirmed (88,512 THB per person per trip for the Middle Eastern market group in 2023, via secondary coverage; not used in the model) | H60: Pending. Pattaya Mail (10 May 2025, https://www.pattayamail.com/latestnews/news/middle-eastern-tourists-top-spending-charts-in-thailand-with-uae-visitors-averaging-over-thb-8800-daily-500402) attributes the figure to TAT 2023 data. The TAT primary document was not fetched.
A61: inputs.csv | B61: tat_spend_per_day_uae_2023 | C61: 8834 | F61: THB per person per day | G61: unconfirmed (8,834 THB per person per day for UAE visitors in 2023, via secondary coverage; not used in the model) | H61: Pending. The same Pattaya Mail article (10 May 2025) attributes the figure to TAT 2023 data. The TAT primary document was not fetched.
A62: inputs.csv | B62: tat_spend_per_night_by_nationality_2024_2025 | F62: THB per person per night | G62: pending (not found in any source read) | H62: No source found. The TAT survey article gives no per-night figures.
A63: inputs.csv | B63: tat_spend_per_trip_by_nationality_2024_2025_official | F63: THB per person per trip | G63: pending (TAT news releases give 2025 partial-year values: China 54,230 THB per trip to 12 December 2025; Singapore 45,000 to September 2025; Japan about 39,000 THB per person to 18 September 2025; three nationalities and periods, so no single value is entered) | H63: https://www.tatnews.org/?p=84576 (TAT news releases; further pages ?p=83305 and ?p=82974)
A64: inputs.csv | B64: mots_spend_per_trip_all_tourists_2019 | C64: 48580 | F64: THB per international tourist per trip | G64: sourced (Ministry of Tourism and Sports, spending per trip of foreign tourists, 2019, preliminary) | H64: https://www.mots.go.th/download/article/article_20200123132729.pdf (Ministry of Tourism and Sports, 2019, preliminary)
A65: inputs.csv | B65: mots_spend_per_day_all_tourists_2019 | C65: 5172.29 | F65: THB per international tourist per day | G65: sourced (Ministry of Tourism and Sports, spending per day of foreign tourists, 2019 full-year summary) | H65: https://www.mots.go.th/download/article/article_20201104090605.pdf (Ministry of Tourism and Sports, 2019 full-year summary)
A66: inputs.csv | B66: intl_avg_length_of_stay_2016_days | C66: 9.6 | F66: days | G66: sourced (NSO Indicators Economic 2562, Table 8.1, average length of stay of international tourists 2016) | H66: https://www.nso.go.th/public/e-book/Indicators-Economic/Indicators-Economic-2562/files/assets/basic-html/page134.html, Table 8.1 (printed page 107), international block, 2016
A67: inputs.csv | B67: intl_avg_length_of_stay_2024_days | C67: 9.4 | F67: days | G67: sourced (MoTS statistics workbook, average length of stay 2024, all international arrivals) | H67: https://www.mots.go.th/images/v2022_c1331820-8936-4423-84cd-65278cebf658.xlsx, sheet Q1-Q4, row Grand Total, column Length of Stay (Days) (2024)
A68: inputs.csv | B68: intl_first_visit_share_2024 | F68: percent of international arrivals on first visit | G68: pending (not found in any source read) | H68: Not found on a fetched TAT page. Niche segment and platform figures are not national and are not used.
A69: inputs.csv | B69: thai_domestic_spend_per_trip_2024 | C69: 4000 | F69: THB per person per domestic trip | G69: unconfirmed (about 4,000 THB per domestic trip, stated as current in an article dated 1 September 2024; no period and no primary source) | H69: No fetched source. A search summary citing TAT domestic data was not verified.
A70: inputs.csv | B70: thai_resident_attraction_visit_share_2024 | F70: percent of attraction visits by Thai residents | G70: pending (not found in any source read) | H70: Not found.
A71: inputs.csv | B71: intl_arrivals_2025 | C71: 32974321 | F71: persons | G71: sourced (MoTS statistics workbook, international arrivals 2025, January to December) | H71: https://www.mots.go.th/images/v2022_5a7fbad7-1fcf-4410-a387-f29bb17486e2.xlsx, sheet Q1-Q4, row Grand Total, column No. of Arrivals (2025)
A72: inputs.csv | B72: intl_arrivals_2024 | C72: 35545714 | F72: persons | G72: sourced (provisional: Ministry of Tourism and Sports workbook, 2024p, January to December; file footer as at 1 January 2026) | H72: https://www.mots.go.th/images/v2022_875a5789-3bcc-4700-bf55-b86fa7f1053c.xlsx (Ministry of Tourism and Sports workbook, Grand Total, 2024p, January to December)
A73: inputs.csv | B73: intl_arrivals_2019 | C73: 39916251 | F73: persons | G73: sourced (Ministry of Tourism and Sports workbook, 2019 year total, revised figure 2562R) | H73: https://www.mots.go.th/download/article/article_20201103140333.xlsx (Ministry of Tourism and Sports workbook, 2019 year total, revised 2562R, updated October 2020)
A74: inputs.csv | B74: intl_arrivals_2020 | C74: 6725000 | F74: persons | G74: sourced (NSO Thai Economic Indicators 2025, Table 8.1, international tourist arrivals 2020) | H74: https://www.nso.go.th/public/e-book/Indicators-Economic/Thai_Economic_Indicators_2025/158, Table 8.1, 2020
A75: inputs.csv | B75: intl_tourism_receipts_2025_mots | C75: 1587.208 | F75: THB bn | G75: sourced (MoTS statistics workbook, tourism receipts 2025; replaces the 2025 candidate of 1,536.574) | H75: https://www.mots.go.th/images/v2022_5a7fbad7-1fcf-4410-a387-f29bb17486e2.xlsx, sheet Q1-Q4, row Grand Total, column Tourism Receipts (1,587,208.17 million baht)
A76: inputs.csv | B76: intl_tourism_receipts_2024_mots | C76: 1612.603 | F76: THB bn | G76: sourced (MoTS statistics workbook, tourism receipts 2024; replaces the news candidate of 1,670) | H76: https://www.mots.go.th/images/v2022_c1331820-8936-4423-84cd-65278cebf658.xlsx, sheet Q1-Q4 (January to December 2024), row Grand Total, column Tourism Receipts (1,612,602.87 million baht)
A77: inputs.csv | B77: intl_tourism_receipts_usd_wdi_2019 | C77: 59.81 | F77: US$ bn | G77: sourced (World Bank WDI ST.INT.TVLR.CD, 2019) | H77: World Bank API, indicator ST.INT.TVLR.CD (international tourism receipts for travel items), Thailand. https://api.worldbank.org/v2/country/THA/indicator/ST.INT.TVLR.CD?format=json&date=2015:2025&per_page=100. Data row 2019. Read through a summarizing fetch, not the raw JSON.
A78: inputs.csv | B78: intl_tourism_receipts_usd_wdi_2020 | C78: 14.198 | F78: US$ bn | G78: sourced (World Bank WDI ST.INT.TVLR.CD, 2020) | H78: World Bank API, indicator ST.INT.TVLR.CD (international tourism receipts for travel items), Thailand. https://api.worldbank.org/v2/country/THA/indicator/ST.INT.TVLR.CD?format=json&date=2015:2025&per_page=100. Data row 2020. Read through a summarizing fetch, not the raw JSON.
A79: inputs.csv | B79: intl_tourism_receipts_bot_thb_bn_2019_2025 | C79: 1400 | F79: THB bn | G79: dropped (the year is ambiguous in the secondary article and the Bank of Thailand series was not reached; not used; the sourced Ministry of Tourism and Sports receipts rows for 2024 and 2025 are used instead) | H79: Bank of Thailand balance-of-payments series (not reached); the secondary article gives 1.4 trillion baht for both 2024 and 2025
A80: inputs.csv | B80: ticket_price_ocean_park_adult_hkd | C80: 498 | F80: HK$ per adult admission | G80: proxy (not current): the 2019 adult admission price, unconfirmed | H80: ocean_park_adult_admission_2019_hkd
A81: inputs.csv | B81: ticket_price_universal_studios_singapore_adult_sgd | C81: 76 | F81: SGD per adult ticket | G81: sourced (Resorts World Sentosa ticket page, Adult Ticket Non-peak, one-day) | H81: https://www.rwsentosa.com/en/play/universal-studios-singapore/tickets, Adult Ticket Non-peak, one-day, age 13 and over (offer from 2026)
A82: inputs.csv | B82: tsa_attraction_recreation_spending_share_2022 | F82: percent of visitor spending on attractions or recreation | G82: pending (not found; the Tourism Satellite Account 2022 summary was too large to read) | H82: Thailand Tourism Satellite Account 2022 executive summary (MoTS). https://www.mots.go.th/images/v2022_1720151556703RXhlY3V0aXZlIHN1bW1hcnkgMjAyMi5wZGY=.pdf. PDF exceeded the fetch size limit. Attraction or recreation share not found.
A83: inputs.csv | B83: hk_disneyland_attendance_fy2019 | C83: 6.5 | F83: million visitors | G83: sourced (Hong Kong Disneyland Annual Business Review FY2019, attendance) | H83: https://hkcorporate.hongkongdisneyland.com/pdf/AnnualBusinessReview19.pdf, Key Business Drivers, printed page 8
A84: inputs.csv | B84: hk_disneyland_attendance_fy2024 | C84: 7.7 | F84: million visitors | G84: sourced (Hong Kong Disneyland Annual Business Review FY2024, attendance) | H84: https://hkcorporate.hongkongdisneyland.com/pdf/AnnualBusinessReview24.pdf, Key Highlights paragraph 2 (PDF page 1) and Key Business Drivers paragraph 15 (PDF page 7)
A85: inputs.csv | B85: hk_disneyland_attendance_fy2025 | C85: 7.5 | F85: million visitors | G85: sourced (Hong Kong Disneyland press release, 28 April 2026: total attendance 7.5 million in fiscal 2025) | H85: https://news.hongkongdisneyland.com/en/press/2026-04-28/ (Hong Kong Disneyland press release, 28 April 2026)
A86: inputs.csv | B86: hk_disneyland_revenue_fy2025_hkd_m | C86: 8694 | F86: HK$ million | G86: sourced (Hong Kong Disneyland Annual Business Review FY2025, total revenue) | H86: https://hkcorporate.hongkongdisneyland.com/pdf/AnnualBusinessReview25.pdf, Key Highlights paragraph 3 (PDF page 1) and key financial results table (PDF page 8)
A87: inputs.csv | B87: hk_disneyland_net_profit_fy2025_hkd_m | C87: 536 | F87: HK$ million | G87: sourced (Hong Kong Disneyland Annual Business Review FY2025, net profit) | H87: https://hkcorporate.hongkongdisneyland.com/pdf/AnnualBusinessReview25.pdf, net profit paragraph 21 (PDF page 9)
A88: inputs.csv | B88: hk_disneyland_adult_ticket_tier1_hkd | C88: 669 | F88: HK$ per adult ticket | G88: sourced (Hong Kong Disneyland published rate, General Admission 1-Day Ticket, Tier 1, undiscounted) | H88: https://www.hongkongdisneyland.com/offers-discounts/travel-industry-salute/, block 1-Day Ticket (Tier 1), read 16 October 2026
A89: inputs.csv | B89: hk_disneyland_adult_ticket_tier4_peak_hkd | C89: 939 | F89: HK$ per adult ticket | G89: sourced (Hong Kong Disneyland published rate, General Admission 1-Day Ticket, Tier 4 peak, undiscounted) | H89: https://www.hongkongdisneyland.com/offers-discounts/travel-industry-salute/, block 1-Day Ticket (Tier 4), read 16 October 2026
A90: inputs.csv | B90: hk_disneyland_visitor_share_local_fy2019 | C90: 41 | F90: percent of attendance | G90: sourced (Hong Kong Disneyland Annual Business Review FY2019, local visitors) | H90: https://hkcorporate.hongkongdisneyland.com/pdf/AnnualBusinessReview19.pdf, Key Business Drivers table, origin of visitors
A91: inputs.csv | B91: hk_disneyland_visitor_share_mainland_fy2019 | C91: 33 | F91: percent of attendance | G91: sourced (Hong Kong Disneyland Annual Business Review FY2019, Mainland China visitors) | H91: https://hkcorporate.hongkongdisneyland.com/pdf/AnnualBusinessReview19.pdf, Key Business Drivers table, origin of visitors
A92: inputs.csv | B92: hk_disneyland_visitor_share_other_fy2019 | C92: 26 | F92: percent of attendance | G92: sourced (Hong Kong Disneyland Annual Business Review FY2019, other markets) | H92: https://hkcorporate.hongkongdisneyland.com/pdf/AnnualBusinessReview19.pdf, Key Business Drivers table, origin of visitors
A93: inputs.csv | B93: ocean_park_attendance_fy2024_25 | C93: 3.46 | F93: million visitors | G93: sourced (Ocean Park results release, FY2024/25, combined dry park and Water World) | H93: https://corporate.oceanpark.com.hk/en/media-partnerships/press-release/ (Ocean Park corporate results, FY2024/25), body paragraph 1
A94: inputs.csv | B94: ocean_park_non_local_visitors_fy2024_25 | C94: 1.25 | F94: million visitors | G94: sourced (Ocean Park results release, FY2024/25, non-local visitors in the same scope) | H94: https://corporate.oceanpark.com.hk/en/media-partnerships/press-release/ (Ocean Park corporate results, FY2024/25), body paragraph 1
... A101: inputs.csv | B101: ocean_park_adult_admission_2019_hkd | C101: 498 | F101: HK$ per adult ticket | G101: unconfirmed (article dated 7 June 2019; the exact effective date is not stated) | H101: Australasian Leisure Management, Entrance prices at Hong Kong's Ocean Park rise by 4%, price rise paragraph, https://www.ausleisure.com.au/news/entrance-prices-at-hong-kongs-ocean-park-rise-by-4. The adult ticket rose to HK$498 from June 2019. Article not fetched; figure from search results.
A102: inputs.csv | B102: universal_studios_singapore_attendance_2024_million | F102: million visitors | G102: pending (not found in any source read) | H102: No annual visitor figure located in a fetched source. Candidate sources: the Genting Singapore annual report for 2024 and any Universal Destinations and Experiences release for 2024.
A103: inputs.csv | B103: lotte_world_adult_ticket_2026_krw | C103: 67000 | F103: KRW per adult ticket (full-day pass) | G103: sourced (secondary: news report of the price rise to 67,000 won, effective 1 April 2026; the official price table was not read; the visitor guide's 62,000 won is not used) | H103: SBS Biz, Lotte World to raise adult ticket price, article dated 17 March 2026, lead paragraph, https://biz.sbs.co.kr/amp/article/20000297877. The article reports a rise from 64,000 won to 67,000 won from 1 April 2026. An English visitor guide for 2026 lists 62,000 won and is not used.
A104: inputs.csv | B104: lotte_world_visitors_2023_million | C104: 5.193 | F104: million persons | G104: sourced (Korea Tourism Organization, Lotte World visitors 2023) | H104: https://know.tour.go.kr/ptourknow/tourgoInfoView19Re.do?seq=103270, 2023 visitor TOP 5 table (5,192,688 persons); same figure in the national TOP 10 endpoint
A105: inputs.csv | B105: lotte_world_visitors_2024_million | C105: 5.257 | F105: million persons | G105: unconfirmed (the operator ranking endpoint gives 5,256,920 for search year 2024; the year is not printed on the response) | H105: https://know.tour.go.kr/stat/visitStatDis/rankingStat.do, search year 2024, rank 4 (5,256,920 persons)
A106: inputs.csv | B106: shanghai_disneyland_attendance_2024_million | C106: 14.7 | F106: million visitors | G106: sourced (government page citing TEA estimate; fetched) | H106: Shanghai Municipal Government news, Shanghai Disneyland secures global top 5 position with record attendance, 27 October 2025, body paragraph on attendance, https://english.shanghai.gov.cn/en-Latest-WhatsNew/20251027/63097f5dd6ff4d2dad7e736573ead8d6.html. The release attributes the figure to the TEA Global Experience Index (the TEA report). It is an estimate, not a Disney total. Calendar year 2024.
A107: inputs.csv | B107: shanghai_disneyland_attendance_2019_million | C107: 11.21 | F107: million visitors | G107: sourced (secondary copy of the TEA and AECOM Theme Index 2019: 11,210,000 for 2019, used as reported; the reporting period is not stated on the copy read) | H107: TEA and AECOM Theme Index 2019, Top 25 table, rank 10 (copy read at https://blooloop.com/files/75972/tea-report-2019.pdf)
A108: inputs.csv | B108: thailand_10y_government_bond_yield_2026_10_14 | C108: 0.0232 | F108: rate per year | G108: sourced (secondary aggregator; Bank of Thailand series not confirmed) | H108: Trading Economics, Thailand 10Y government bond yield, headline value for 14 October 2026, https://tradingeconomics.com/thailand/government-bond-yield. Secondary aggregator. The Bank of Thailand series was not reached (bot.or.th returned HTTP 404).
A109: inputs.csv | B109: corporate_income_tax_rate_standard | C109: 0.2 | F109: rate of net profit | G109: sourced (Revenue Department English corporate income tax page: 20 percent on net profit; the page was last updated in 2020) | H109: https://www.rd.go.th/english/6044.html (Revenue Department English corporate income tax page)
A110: inputs.csv | B110: vat_statutory_rate | C110: 0.1 | F110: rate | G110: sourced (Revenue Department English VAT page: statutory rate 10.00 percent) | H110: https://www.rd.go.th/english/37732.html (Revenue Department English VAT page)
A111: inputs.csv | B111: vat_reduced_rate_2026_2027 | C111: 0.07 | F111: rate, including local tax | G111: sourced (KPMG summary of Royal Decree No. 807: 7 percent including local tax for 1 October 2026 to 30 September 2027; the Royal Gazette text was not read) | H111: KPMG TaxNewsFlash, same article, first paragraph on Royal Decree No. 807. Temporary reduced rate for 1 October 2026 to 30 September 2027. It must be checked again after 30 September 2027.
A112: inputs.csv | B112: adb_economic_horizon_years_low | C112: 20 | F112: years | G112: sourced (ADB 2017; international guidance) | H112: ADB (2017) Guidelines for the Economic Analysis of Projects, printed pages 47 to 48, paragraph 176, https://www.adb.org/sites/default/files/institutional-document/32256/economic-analysis-projects.pdf. Lower bound of the 20 to 30 year range for project flows. International guidance, not a Thai value.
A113: inputs.csv | B113: adb_economic_horizon_years_high | C113: 30 | F113: years | G113: sourced (ADB 2017; international guidance) | H113: ADB (2017) Guidelines for the Economic Analysis of Projects, printed pages 47 to 48, paragraph 176, https://www.adb.org/sites/default/files/institutional-document/32256/economic-analysis-projects.pdf. Upper bound of the 20 to 30 year range. International guidance, not a Thai value.
A114: inputs.csv | B114: adb_dam_railway_operating_years_low | C114: 20 | F114: years | G114: sourced (ADB 2017; asset type dams and railways) | H114: ADB (2017), printed page 64, Appendix 3, paragraph 2, https://www.adb.org/sites/default/files/institutional-document/32256/economic-analysis-projects.pdf. Lower bound of the 20 to 25 year operating life for dams and railways.
... A142: inputs.csv | B142: cbre_pattaya_occupancy_h2_2025 | C142: 0.655 | F142: share | G142: sourced (secondary: CBRE broker data, H2 2025 occupancy 65.5%; not an official source) | H142: CBRE, Pattaya Overall Figures H2 2025, https://mktgdocs.cbre.com/2299/175bc843-73b5-4940-a859-14bd0f57a6a1-1295998069/Pattaya-Overall-Figures-H2-202.pdf (occupancy)
A143: assumptions.csv | B143: project_life_years | C143: 20 | D143: 20 | E143: 25 | F143: years | G143: assumption (team recommendation adopted; anchored to sourced ranges; not sourced as a Thai value; confirmed by the team on 19 October 2026) | H143: Team recommendation adopted on the leader's instruction. Base 20 years: the Revenue Department tax depreciation rate for durable buildings is 5 percent of cost a year (input row asset_useful_life_by_type_nesdc_years), which corresponds to 20 years for the building component. That is a tax rate, not an economic life. Low 20 is the lower bound of the ADB (2017) horizon of 20 to 30 years (input rows adb_economic_horizon_years_low and _high). High 25 is the upper bound of the ADB operating life for dams and railways of 20 to 25 years (input rows adb_dam_railway_operating_years_low and _high).
A144: assumptions.csv | B144: construction_years | C144: 2 | D144: 3 | E144: 2 | F144: years | G144: generalized (ADB 2017 illustrative 2-year implementation period; confirmed by the team on 19 October 2026) | H144: Base and high use the ADB (2017) illustrative implementation period of 2 years (input row adb_illustrative_implementation_years). The low case adds one year for a complex of this size. That step is a judgement and is not sourced.
A145: assumptions.csv | B145: wacc_financial | C145: 0.08 | D145: 0.1 | E145: 0.07 | F145: rate | G145: assumption (team recommendation adopted; not sourced; confirmed by the team on 19 October 2026) | H145: Team recommendation adopted on the leader's instruction. Base 0.08 is the NESDC (2024) social discount rate of 7 percent plus one point for operator risk. No financial rate for a Thai theme park was found in the sources, so this is an assumption. Low 0.10 is two points above the base for a more pessimistic operator. High 0.07 equals the NESDC social rate. The ADB (2017) standard EIRR of 0.09 (input row discount_rate_eirr_standard) is an economic hurdle and is not used. The Thai 10-year government bond yield of 2.32 percent (input row thailand_10y_government_bond_yield_2026_10_14) is a floor reference and is not a WACC.
A146: assumptions.csv | B146: attendance_million_per_year | C146: 7.5 | D146: 3.46 | E146: 14.7 | F146: million visits per year | G146: generalized (Hong Kong Disneyland FY2025 base; Ocean Park FY2024/25 low; Shanghai Disneyland 2024 high; confirmed by the team on 19 October 2026) | H146: Team recommendation adopted: the working value is kept. The base is the Hong Kong Disneyland FY2025 attendance reported by the operator (input row hk_disneyland_attendance_fy2025). Base is Hong Kong Disneyland attendance in fiscal 2025 (input row hk_disneyland_attendance_fy2025). Low is Ocean Park attendance in fiscal 2024/25 (input row ocean_park_attendance_fy2024_25). High is Shanghai Disneyland attendance in 2024 (input row shanghai_disneyland_attendance_2024_million), which is a TEA estimate. These parks are comparables and not the Thai complex. The demand study has not reported.
A147: assumptions.csv | B147: international_share | C147: 0.59 | D147: 0.36 | E147: 0.75 | F147: share of attendance | G147: generalized (Hong Kong Disneyland FY2019 base, itself unconfirmed; low is an assumed value after an unconfirmed Ocean Park anchor; high not anchored; confirmed by the team on 19 October 2026) | H147: Base is the share of Hong Kong Disneyland visitors who are not local residents in fiscal 2019, 59 percent, which is 100 minus the 41 percent local share (input row hk_disneyland_visitor_share_local_fy2019; a copy on a secondary blog, not confirmed). Low 0.36 is an assumed value. It was once taken as the Ocean Park non-local share in fiscal 2024/25 (1.25 of 3.46 million), but that count is not confirmed (input row ocean_park_non_local_visitors_fy2024_25 is pending). High is not anchored and is an assumed 75 percent. The non-local count includes mainland visitors, which the model treats as international visitors.
A148: assumptions.csv | B148: incremental_share | C148: 0.3 | D148: 0.1 | E148: 0.5 | F148: share | G148: assumption (labelled grid; not sourced; confirmed by the team on 19 October 2026) | H148: Team recommendation adopted: the working value is kept. No source exists; the labelled range is the sensitivity. No comparable value in the project sources. Share of international visits that are new to Thailand or to its tourism spending. Placeholder for the segment study.
A149: assumptions.csv | B149: displacement_share | C149: 0.3 | D149: 0.5 | E149: 0.1 | F149: share | G149: assumption (labelled grid; not sourced; confirmed by the team on 19 October 2026) | H149: Team recommendation adopted: the working value is kept. No source exists; the labelled range is the sensitivity. Share of gross spending moved from other Thai destinations or activities. The low case is the highest displacement. No source in the project sources. Placeholder for the segment study.
A150: assumptions.csv | B150: spend_per_visit_thb | C150: 10000 | D150: 1862 | E150: 20000 | F150: THB per incremental visit | G150: assumption (labelled grid; low case from a sourced on-site benchmark and the Bank of Thailand yen rate of 12 October 2026; confirmed by the team on 19 October 2026) | H150: Team decisions adopted for the base and high cases: the labelled placeholders of 10,000 and 20,000 THB are kept. The low case is the sourced on-site benchmark: Oriental Land's Tokyo Disney Resort per-guest merchandise (5,227 yen) and food and beverage (3,569 yen) sales for FY3/2026, 8,796 yen in total, converted at 0.211734 THB per yen, the Bank of Thailand JPY mid rate for 12 October 2026 (21.1734 THB per 100 yen), the same date as the dollar reference rate in the input table. The benchmark measures on-site spending only, so it is a floor for incremental visitors and not a base. The per-trip figures (TAT 2023 at 50,900 THB; MoTS 2019 at 48,580 THB) are per trip, not per park visit, and are not used. Values are labelled assumptions for the spending study.
A151: assumptions.csv | B151: domestic_retention_share | C151: 0.5 | D151: 0.3 | E151: 0.7 | F151: share | G151: assumption (labelled grid; not sourced; confirmed by the team on 19 October 2026) | H151: Team recommendation adopted: the working value is kept. No source exists; the labelled range is the sensitivity. Share of net spending that stays in the Thai economy after imports and leakage. Placeholder for the economic study.
A152: assumptions.csv | B152: tax_share_of_spend | C152: 0.065421 | D152: 0 | E152: 0.090909 | F152: share of net spending | G152: assumption (labelled grid; not sourced; confirmed by the team on 19 October 2026) | H152: The tax base is not documented, so this is a placeholder. Base is 7 divided by 107, the tax-inclusive share of spending at the reduced 7 percent VAT rate in force from 1 October 2026 (input row vat_reduced_rate_2026_2027). High is 10 divided by 110, at the statutory 10 percent rate (input row vat_statutory_rate). Low captures no tax.
A153: assumptions.csv | B153: opex_share | C153: 0.9383 | D153: 1.2146 | E153: 0.7 | F153: ratio of revenue | G153: generalized (Hong Kong Disneyland FY2025 base; Ocean Park FY2024/25 low; high not anchored; confirmed by the team on 19 October 2026) | H153: Base is Hong Kong Disneyland fiscal 2025 costs as a share of revenue: (8694 minus 536) divided by 8694, which is 0.9383. Low is Ocean Park fiscal 2024/25 costs as a share of revenue: (1280 plus 274.7) divided by 1280, which is 1.2146, using the press revenue of HK$1.28 billion. High is not anchored and is an assumed 0.70. Both anchors are total costs implied by net profit or loss. They include depreciation, financing and tax. Depreciation is included by the leader's decision, so the anchors are total costs as implied by net profit or loss and are not restated to cash operating cost. The overlap with the capital cost in the operator ledger, and in the national ledger, is kept, which makes the operating results pessimistic.
A154: assumptions.csv | B154: ticket_revenue_per_visit_thb | C154: 2877 | D154: 2158 | E154: 4038 | F154: THB per visit | G154: generalized (Hong Kong Disneyland adult prices at an assumed exchange rate; low is a grid discount; confirmed by the team on 19 October 2026) | H154: Base is the Hong Kong Disneyland adult Tier 1 ticket of HK$669 (input row hk_disneyland_adult_ticket_tier1_hkd), converted at 4.3 baht per Hong Kong dollar. The rate is the Bank of Thailand reference rate of 33.52 baht per US dollar on 12 October 2026 (input row exchange_rate_thb_per_usd) divided by an assumed 7.8 Hong Kong dollars per US dollar. High is the Tier 4 peak adult ticket of HK$939 (input row hk_disneyland_adult_ticket_tier4_peak_hkd) at the same rate. Low is 25 percent below the base for discounts and resident or child pricing, a grid choice. Adult list prices are an upper reference for average revenue per visit.
... A163: assumptions.csv | B163: occupancy_ceiling_serving_site | C163: 0.85 | D163: 0.8042 | E163: 0.9 | F163: share | G163: assumption (low anchored to the highest 2024 occupancy of any province; base and high assumed; not sourced; confirmed by the team on 19 October 2026) | H163: Practical maximum average occupancy. The accommodation headroom is the free room stock up to this ceiling, rooms times (ceiling minus occupancy), floored at zero, so that headroom is not measured to 100 percent occupancy. The low case is the highest 2024 occupancy observed in any Thai province: Chon Buri at 80.42 percent (National Statistical Office Table 17.1, input row chonburi_occupancy_2024_tat). Chon Buri ranks first of the 77 rows of the table, including Bangkok, and the next value is 80.12 percent. Under the low case the market has no free rooms, so the low case has no accommodation headroom. The base case (85 percent) and high case (90 percent) are assumed practical maximums above any observed rate. No source gives a ceiling. A base ceiling anchored to the observed maximum (80.42 percent) would give zero headroom in the base case as well.

Sheet Appraisal
A1: Operator financial appraisal: legacy-model reconciliation and cash-cost proxy (base case, THB billion unless stated)
A2: Legacy-model reconciliation using the original cost scope, with a separate cash-cost proxy. Results remain provisional. Years t = 0 to 22 from the start of construction. Cells are formulas linked to Inputs.
A3: Limits: not a complete Financial Appraisal. The cash basis is a proxy from Hong Kong Disneyland FY2025 accounts. Not modelled: cash tax, replacement capex, working capital, and the park-only capex and revenue boundary. The depreciation treatment is pending the team decision.
A4: Parameter | B4: Confirmed basis | C4: Cash basis
A5: Operating-cost share of revenue | B5: =Inputs!$C$153 | C5: =Inputs!$C$135/Inputs!$C$86
A6: WACC (financial cost of capital) | B6: =Inputs!$C$145 | C6: =B6
A7: Project life (years of operation) | B7: =Inputs!$C$143
A8: Construction years | B8: =Inputs!$C$144
A9: Capital expenditure (THB bn, proposal value, not verified) | B9: =Inputs!$C$4
A10: Attendance (million visits a year) | B10: =Inputs!$C$146
A11: International share of attendance | B11: =Inputs!$C$147
A12: Physical visit cap (million visits a year): smaller of airport and room-stock capacity | B12: =MIN(Inputs!$C$28/Inputs!$C$157,Inputs!$C$161*365*Inputs!$C$156/Inputs!$C$155)/1000000
A13: Ticket revenue per visit (THB) | B13: =Inputs!$C$154
A14: Operator visits per operating year (million): attendance less international visits above the cap | B14: =B10-MAX(B10*B11-B12,0)
A15: Operator revenue per operating year (THB bn) | B15: =B14*B13/1000
A17: Results | B17: Confirmed basis | C17: Cash basis
A18: Operator NPV at the financial cost of capital (THB bn) | B18: =SUM(J31:J53) | C18: =SUM(N31:N53)
A19: Operator IRR | B19: =IRR(I31:I53) | C19: =IRR(M31:M53)
A20: Break-even capital expenditure (THB bn), NPV = 0 | B20: =B9*(B15*(1-B5)*B26)/B27 | C20: =B9*(B15*(1-C5)*B26)/B27
A21: Break-even attendance (million visits a year), NPV = 0 | B21: =B10-B18/((1-B5)*B13/1000*(1-B11)*B26) | C21: =B10-C18/((1-C5)*B13/1000*(1-B11)*B26)
A22: Regime check for break-even attendance (OK when the break-even attendance is above the cap) | B22: =IF(B21*B11>=B12,"OK","CHECK") | C22: =IF(C21*B11>=B12,"OK","CHECK")
A23: Model reference NPV (scratch run of the model, 20 Oct 2026; for audit only) | B23: -280.94127 | C23: -259.41978
A24: Difference from the model reference (should be about 0) | B24: =B18-B23 | C24: =C18-C23
A26: Sum of discount factors over operating years (AF0) | B26: =SUMPRODUCT(B31:B53,D31:D53)
A27: Present value of capital expenditure at the proposal value (PVcap, THB bn) | B27: =SUMPRODUCT(E31:E53,B31:B53)
A30: Year t | B30: Discount factor | C30: Construction flag | D30: Operating flag | E30: Capex (THB bn) | F30: Operator visits (million) | G30: Revenue (THB bn) | H30: Opex, confirmed (THB bn) | I30: Cash flow, confirmed | J30: PV, confirmed | K30: Cumulative, confirmed | L30: Opex, cash basis (THB bn) | M30: Cash flow, cash basis | N30: PV, cash basis | O30: Cumulative, cash basis
A31: 0 | B31: =1/(1+$B$6)^A31 | C31: =IF(A31<$B$8,1,0) | D31: =IF(AND(A31>=$B$8,A31<$B$8+$B$7),1,0) | E31: =C31*$B$9/$B$8 | F31: =D31*$B$14 | G31: =F31*$B$13/1000 | H31: =$B$5*G31 | I31: =G31-H31-E31 | J31: =I31*B31 | K31: =SUM($I$31:I31) | L31: =$C$5*G31 | M31: =G31-L31-E31 | N31: =M31*B31 | O31: =SUM($M$31:M31)
A32: 1 | B32: =1/(1+$B$6)^A32 | C32: =IF(A32<$B$8,1,0) | D32: =IF(AND(A32>=$B$8,A32<$B$8+$B$7),1,0) | E32: =C32*$B$9/$B$8 | F32: =D32*$B$14 | G32: =F32*$B$13/1000 | H32: =$B$5*G32 | I32: =G32-H32-E32 | J32: =I32*B32 | K32: =SUM($I$31:I32) | L32: =$C$5*G32 | M32: =G32-L32-E32 | N32: =M32*B32 | O32: =SUM($M$31:M32)
A33: 2 | B33: =1/(1+$B$6)^A33 | C33: =IF(A33<$B$8,1,0) | D33: =IF(AND(A33>=$B$8,A33<$B$8+$B$7),1,0) | E33: =C33*$B$9/$B$8 | F33: =D33*$B$14 | G33: =F33*$B$13/1000 | H33: =$B$5*G33 | I33: =G33-H33-E33 | J33: =I33*B33 | K33: =SUM($I$31:I33) | L33: =$C$5*G33 | M33: =G33-L33-E33 | N33: =M33*B33 | O33: =SUM($M$31:M33)
A34: 3 | B34: =1/(1+$B$6)^A34 | C34: =IF(A34<$B$8,1,0) | D34: =IF(AND(A34>=$B$8,A34<$B$8+$B$7),1,0) | E34: =C34*$B$9/$B$8 | F34: =D34*$B$14 | G34: =F34*$B$13/1000 | H34: =$B$5*G34 | I34: =G34-H34-E34 | J34: =I34*B34 | K34: =SUM($I$31:I34) | L34: =$C$5*G34 | M34: =G34-L34-E34 | N34: =M34*B34 | O34: =SUM($M$31:M34)
A35: 4 | B35: =1/(1+$B$6)^A35 | C35: =IF(A35<$B$8,1,0) | D35: =IF(AND(A35>=$B$8,A35<$B$8+$B$7),1,0) | E35: =C35*$B$9/$B$8 | F35: =D35*$B$14 | G35: =F35*$B$13/1000 | H35: =$B$5*G35 | I35: =G35-H35-E35 | J35: =I35*B35 | K35: =SUM($I$31:I35) | L35: =$C$5*G35 | M35: =G35-L35-E35 | N35: =M35*B35 | O35: =SUM($M$31:M35)
A36: 5 | B36: =1/(1+$B$6)^A36 | C36: =IF(A36<$B$8,1,0) | D36: =IF(AND(A36>=$B$8,A36<$B$8+$B$7),1,0) | E36: =C36*$B$9/$B$8 | F36: =D36*$B$14 | G36: =F36*$B$13/1000 | H36: =$B$5*G36 | I36: =G36-H36-E36 | J36: =I36*B36 | K36: =SUM($I$31:I36) | L36: =$C$5*G36 | M36: =G36-L36-E36 | N36: =M36*B36 | O36: =SUM($M$31:M36)
A37: 6 | B37: =1/(1+$B$6)^A37 | C37: =IF(A37<$B$8,1,0) | D37: =IF(AND(A37>=$B$8,A37<$B$8+$B$7),1,0) | E37: =C37*$B$9/$B$8 | F37: =D37*$B$14 | G37: =F37*$B$13/1000 | H37: =$B$5*G37 | I37: =G37-H37-E37 | J37: =I37*B37 | K37: =SUM($I$31:I37) | L37: =$C$5*G37 | M37: =G37-L37-E37 | N37: =M37*B37 | O37: =SUM($M$31:M37)
A38: 7 | B38: =1/(1+$B$6)^A38 | C38: =IF(A38<$B$8,1,0) | D38: =IF(AND(A38>=$B$8,A38<$B$8+$B$7),1,0) | E38: =C38*$B$9/$B$8 | F38: =D38*$B$14 | G38: =F38*$B$13/1000 | H38: =$B$5*G38 | I38: =G38-H38-E38 | J38: =I38*B38 | K38: =SUM($I$31:I38) | L38: =$C$5*G38 | M38: =G38-L38-E38 | N38: =M38*B38 | O38: =SUM($M$31:M38)
A39: 8 | B39: =1/(1+$B$6)^A39 | C39: =IF(A39<$B$8,1,0) | D39: =IF(AND(A39>=$B$8,A39<$B$8+$B$7),1,0) | E39: =C39*$B$9/$B$8 | F39: =D39*$B$14 | G39: =F39*$B$13/1000 | H39: =$B$5*G39 | I39: =G39-H39-E39 | J39: =I39*B39 | K39: =SUM($I$31:I39) | L39: =$C$5*G39 | M39: =G39-L39-E39 | N39: =M39*B39 | O39: =SUM($M$31:M39)
A40: 9 | B40: =1/(1+$B$6)^A40 | C40: =IF(A40<$B$8,1,0) | D40: =IF(AND(A40>=$B$8,A40<$B$8+$B$7),1,0) | E40: =C40*$B$9/$B$8 | F40: =D40*$B$14 | G40: =F40*$B$13/1000 | H40: =$B$5*G40 | I40: =G40-H40-E40 | J40: =I40*B40 | K40: =SUM($I$31:I40) | L40: =$C$5*G40 | M40: =G40-L40-E40 | N40: =M40*B40 | O40: =SUM($M$31:M40)
A41: 10 | B41: =1/(1+$B$6)^A41 | C41: =IF(A41<$B$8,1,0) | D41: =IF(AND(A41>=$B$8,A41<$B$8+$B$7),1,0) | E41: =C41*$B$9/$B$8 | F41: =D41*$B$14 | G41: =F41*$B$13/1000 | H41: =$B$5*G41 | I41: =G41-H41-E41 | J41: =I41*B41 | K41: =SUM($I$31:I41) | L41: =$C$5*G41 | M41: =G41-L41-E41 | N41: =M41*B41 | O41: =SUM($M$31:M41)
A42: 11 | B42: =1/(1+$B$6)^A42 | C42: =IF(A42<$B$8,1,0) | D42: =IF(AND(A42>=$B$8,A42<$B$8+$B$7),1,0) | E42: =C42*$B$9/$B$8 | F42: =D42*$B$14 | G42: =F42*$B$13/1000 | H42: =$B$5*G42 | I42: =G42-H42-E42 | J42: =I42*B42 | K42: =SUM($I$31:I42) | L42: =$C$5*G42 | M42: =G42-L42-E42 | N42: =M42*B42 | O42: =SUM($M$31:M42)
... A53: 22 | B53: =1/(1+$B$6)^A53 | C53: =IF(A53<$B$8,1,0) | D53: =IF(AND(A53>=$B$8,A53<$B$8+$B$7),1,0) | E53: =C53*$B$9/$B$8 | F53: =D53*$B$14 | G53: =F53*$B$13/1000 | H53: =$B$5*G53 | I53: =G53-H53-E53 | J53: =I53*B53 | K53: =SUM($I$31:I53) | L53: =$C$5*G53 | M53: =G53-L53-E53 | N53: =M53*B53 | O53: =SUM($M$31:M53)
A55: Sensitivity cases (formula-based). The model reference column is the scratch run of the model on the confirmed basis.
A56: Case | B56: Capex factor | C56: Opex factor | D56: Revenue factor | E56: Opening delay (years) | F56: Annuity factor AFk | G56: Operator NPV, confirmed (THB bn) | H56: Operator NPV, cash basis (THB bn) | I56: Model reference, confirmed (THB bn) | J56: Difference (should be about 0)
A57: base | B57: 1 | C57: 1 | D57: 1 | E57: 0 | F57: =SUMPRODUCT($B$31:$B$53*($A$31:$A$53>=$B$8+E57)*($A$31:$A$53<$B$8+E57+$B$7)) | G57: =(D57-C57*$B$5)*$B$15*F57-B57*$B$27 | H57: =(D57-C57*$C$5)*$B$15*F57-B57*$B$27 | I57: -280.94127 | J57: =G57-I57
A58: construction cost up 5 percent | B58: 1.05 | C58: 1 | D58: 1 | E58: 0 | F58: =SUMPRODUCT($B$31:$B$53*($A$31:$A$53>=$B$8+E58)*($A$31:$A$53<$B$8+E58+$B$7)) | G58: =(D58-C58*$B$5)*$B$15*F58-B58*$B$27 | H58: =(D58-C58*$C$5)*$B$15*F58-B58*$B$27 | I58: -295.38571 | J58: =G58-I58
A59: construction cost down 5 percent | B59: 0.95 | C59: 1 | D59: 1 | E59: 0 | F59: =SUMPRODUCT($B$31:$B$53*($A$31:$A$53>=$B$8+E59)*($A$31:$A$53<$B$8+E59+$B$7)) | G59: =(D59-C59*$B$5)*$B$15*F59-B59*$B$27 | H59: =(D59-C59*$C$5)*$B$15*F59-B59*$B$27 | I59: -266.49683 | J59: =G59-I59
A60: construction cost up 10 percent | B60: 1.1 | C60: 1 | D60: 1 | E60: 0 | F60: =SUMPRODUCT($B$31:$B$53*($A$31:$A$53>=$B$8+E60)*($A$31:$A$53<$B$8+E60+$B$7)) | G60: =(D60-C60*$B$5)*$B$15*F60-B60*$B$27 | H60: =(D60-C60*$C$5)*$B$15*F60-B60*$B$27 | I60: -309.83016 | J60: =G60-I60
A61: construction cost down 10 percent | B61: 0.9 | C61: 1 | D61: 1 | E61: 0 | F61: =SUMPRODUCT($B$31:$B$53*($A$31:$A$53>=$B$8+E61)*($A$31:$A$53<$B$8+E61+$B$7)) | G61: =(D61-C61*$B$5)*$B$15*F61-B61*$B$27 | H61: =(D61-C61*$C$5)*$B$15*F61-B61*$B$27 | I61: -252.05238 | J61: =G61-I61
A62: construction cost up 20 percent | B62: 1.2 | C62: 1 | D62: 1 | E62: 0 | F62: =SUMPRODUCT($B$31:$B$53*($A$31:$A$53>=$B$8+E62)*($A$31:$A$53<$B$8+E62+$B$7)) | G62: =(D62-C62*$B$5)*$B$15*F62-B62*$B$27 | H62: =(D62-C62*$C$5)*$B$15*F62-B62*$B$27 | I62: -338.71905 | J62: =G62-I62
A63: construction cost down 20 percent | B63: 0.8 | C63: 1 | D63: 1 | E63: 0 | F63: =SUMPRODUCT($B$31:$B$53*($A$31:$A$53>=$B$8+E63)*($A$31:$A$53<$B$8+E63+$B$7)) | G63: =(D63-C63*$B$5)*$B$15*F63-B63*$B$27 | H63: =(D63-C63*$C$5)*$B$15*F63-B63*$B$27 | I63: -223.16349 | J63: =G63-I63
A64: operating and maintenance cost up 5 percent | B64: 1 | C64: 1.05 | D64: 1 | E64: 0 | F64: =SUMPRODUCT($B$31:$B$53*($A$31:$A$53>=$B$8+E64)*($A$31:$A$53<$B$8+E64+$B$7)) | G64: =(D64-C64*$B$5)*$B$15*F64-B64*$B$27 | H64: =(D64-C64*$C$5)*$B$15*F64-B64*$B$27 | I64: -286.98442 | J64: =G64-I64
A65: operating and maintenance cost down 5 percent | B65: 1 | C65: 0.95 | D65: 1 | E65: 0 | F65: =SUMPRODUCT($B$31:$B$53*($A$31:$A$53>=$B$8+E65)*($A$31:$A$53<$B$8+E65+$B$7)) | G65: =(D65-C65*$B$5)*$B$15*F65-B65*$B$27 | H65: =(D65-C65*$C$5)*$B$15*F65-B65*$B$27 | I65: -274.89812 | J65: =G65-I65
A66: operating and maintenance cost up 10 percent | B66: 1 | C66: 1.1 | D66: 1 | E66: 0 | F66: =SUMPRODUCT($B$31:$B$53*($A$31:$A$53>=$B$8+E66)*($A$31:$A$53<$B$8+E66+$B$7)) | G66: =(D66-C66*$B$5)*$B$15*F66-B66*$B$27 | H66: =(D66-C66*$C$5)*$B$15*F66-B66*$B$27 | I66: -293.02758 | J66: =G66-I66
A67: operating and maintenance cost down 10 percent | B67: 1 | C67: 0.9 | D67: 1 | E67: 0 | F67: =SUMPRODUCT($B$31:$B$53*($A$31:$A$53>=$B$8+E67)*($A$31:$A$53<$B$8+E67+$B$7)) | G67: =(D67-C67*$B$5)*$B$15*F67-B67*$B$27 | H67: =(D67-C67*$C$5)*$B$15*F67-B67*$B$27 | I67: -268.85496 | J67: =G67-I67
A68: operating and maintenance cost up 20 percent | B68: 1 | C68: 1.2 | D68: 1 | E68: 0 | F68: =SUMPRODUCT($B$31:$B$53*($A$31:$A$53>=$B$8+E68)*($A$31:$A$53<$B$8+E68+$B$7)) | G68: =(D68-C68*$B$5)*$B$15*F68-B68*$B$27 | H68: =(D68-C68*$C$5)*$B$15*F68-B68*$B$27 | I68: -305.11388 | J68: =G68-I68
... A82: one-year delay in opening | B82: 1 | C82: 1 | D82: 1 | E82: 1 | F82: =SUMPRODUCT($B$31:$B$53*($A$31:$A$53>=$B$8+E82)*($A$31:$A$53<$B$8+E82+$B$7)) | G82: =(D82-C82*$B$5)*$B$15*F82-B82*$B$27 | H82: =(D82-C82*$C$5)*$B$15*F82-B82*$B$27 | I82: -281.52998 | J82: =G82-I82

Sheet Charts
A1: Charts built from the Appraisal sheet (native Excel charts linked to the cells, so they update with the inputs)
