Workbook

Sheet Inputs
A1: Parameter | B1: Unit | C1: Value (base case) | D1: Low case | E1: High case | F1: Source
A2: Capex park high thb bn | B2: THB bn | C2: 200 | F2: Thai park proposal, news reports (12 and 15 May 2026)
A3: Capex park low thb bn | B3: THB bn | C3: 100 | F3: Thai park proposal, news report (27 March 2026)
A4: Claim additional visitors million per year | B4: million visits per year | C4: 10 | F4: Thai government proposal claims, news reports (2026)
A5: Claim revenue thb bn | B5: THB bn | C5: 150 | F5: Thai government proposal claims, news reports (2026)
A6: Claim share of gdp percent per year | B6: percent per year of GDP growth | C6: 1 | F6: Thai government proposal claims, news reports (2026)
A7: Discount rate eirr standard | B7: rate | C7: 0.09 | F7: ADB (2017) Guidelines for the Economic Analysis of Projects, paragraph 194 (printed page 53); DOI. http://dx.doi.org/10.22617/TIM178607-2
A8: Discount rate eirr social sector | B8: rate | C8: 0.06 | F8: ADB (2017) Guidelines for the Economic Analysis of Projects, paragraph 194 (printed page 53); DOI. http://dx.doi.org/10.22617/TIM178607-2
A9: Discount rate social nesdc | B9: rate | C9: 0.07 | F9: NESDC (2024) Guide to Public Investment Project Appraisal, section 6.2.2 (PDF page 28); range in section 6.2.1 (PDF page 26); URL. https://www.nesdc.go.th/wp-content/uploads/2025/05/article_20241009124821.pdf
A10: Discount rate social nesdc pre2025 | B10: rate | C10: 0.12 | F10: NESDC (2024) Guide to Public Investment Project Appraisal, section 6.2.2 (PDF page 28); URL. https://www.nesdc.go.th/wp-content/uploads/2025/05/article_20241009124821.pdf
A11: Conversion factor standard | B11: ratio | C11: 0.7 | F11: NESDC (2024) Guide to Public Investment Project Appraisal, summary of changes (PDF page 5); used when shadow prices cannot be computed; URL. https://www.nesdc.go.th/wp-content/uploads/2025/05/article_20241009124821.pdf
A12: Project life years | B12: years | C12: 20 | F12: NESDC Requirement
A13: Wacc financial | B13: rate | C13: 0.08 | F13: NESDC Requirement
... A47: Chonburi foreign arrivals 2019 | B47: persons | C47: 9966574 | F47: https://intelligencecenter.tat.or.th/articles/9907
A48: Utapao expansion progress overall percent | B48: percent complete | F48: https://www.eeco.or.th/en/u-tapao-airport-and-eastern-aviation-city/
A49: Utapao expansion opening year | B49: calendar year | C49: 2031 | F49: https://www.britishaviationgroup.co.uk/?p=24880
A50: High speed rail full service year eeco | B50: calendar year | C50: 2031 | F50: High-speed rail linking three airports, EEC Office. https://www.eeco.or.th/en/high-speed-rail-linking-three-airports/
A51: High speed rail full service year wikipedia | B51: calendar year | C51: 2029 | F51: Don Mueang-Suvarnabhumi-U-Tapao high-speed railway, Wikipedia. https://en.wikipedia.org/wiki/Don_Mueang%E2%80%93Suvarnabhumi%E2%80%93U-Tapao_high-speed_railway
A52: High speed rail status sep 2026 | B52: text | F52: Uttapao and High-Speed Rail: EEC's Make-or-Break Infrastructure Bet, Nation Thailand (7 Sep 2026). https://www.nationthailand.com/business/economy/40070765
A53: Motorway7 utapao extension length km | B53: kilometres | C53: 1.92 | F53: ADB news release, Thailand EEC infrastructure, 6 June 2025. https://www.adb.org/news/adb-supports-resilient-infrastructure-development-eastern-thailand
A54: Motorway7 utapao extension completion year | B54: calendar year | C54: 2028 | F54: https://www.thansettakij.com/economy/megaproject/630463
A55: Pattaya map ta phut motorway7 opening year | B55: calendar year (opened August 2020) | C55: 2020 | F55: Thai Prime Minister opens Pattaya-Map Ta Phut Highway, Pattaya Mail (24 Aug 2020). https://www.pattayamail.com/news/thai-prime-minister-opens-pattaya-map-ta-phut-highway-312223
A56: Tat spend per trip all nationalities 2023 | B56: THB per trip | C56: 50900 | F56: No external source located
A57: Tat spend per trip middle eastern 2023 | B57: THB per person per trip | C57: 88512 | F57: No external source located
A58: Tat spend per day uae 2023 | B58: THB per person per day | C58: 8834 | F58: No external source located
A59: Tat spend per night by nationality 2024 2025 | B59: THB per person per night | F59: No external source located
A60: Tat spend per trip by nationality 2024 2025 official | B60: THB per person per trip | F60: https://www.tatnews.org/?p=84576
A61: Mots spend per trip all tourists 2019 | B61: THB per international tourist per trip | C61: 48580 | F61: https://www.mots.go.th/download/article/article_20200123132729.pdf
A62: Mots spend per day all tourists 2019 | B62: THB per international tourist per day | C62: 5172.29 | F62: https://www.mots.go.th/download/article/article_20201104090605.pdf
A63: Intl avg length of stay 2016 days | B63: days | C63: 9.6 | F63: https://www.nso.go.th/public/e-book/Indicators-Economic/Indicators-Economic-2562/files/assets/basic-html/page134.html
A64: Intl avg length of stay 2024 days | B64: days | C64: 9.4 | F64: https://www.mots.go.th/images/v2022_c1331820-8936-4423-84cd-65278cebf658.xlsx
A65: Intl first visit share 2024 | B65: percent of international arrivals on first visit | F65: No external source located
A66: Thai domestic spend per trip 2024 | B66: THB per person per domestic trip | C66: 4000 | F66: No external source located
A67: Thai resident attraction visit share 2024 | B67: percent of attraction visits by Thai residents | F67: No external source located
A68: Intl arrivals 2025 | B68: persons | C68: 32974321 | F68: https://www.mots.go.th/images/v2022_5a7fbad7-1fcf-4410-a387-f29bb17486e2.xlsx
A69: Intl arrivals 2024 | B69: persons | C69: 35545714 | F69: https://www.mots.go.th/images/v2022_875a5789-3bcc-4700-bf55-b86fa7f1053c.xlsx
A70: Intl arrivals 2019 | B70: persons | C70: 39916251 | F70: https://www.mots.go.th/download/article/article_20201103140333.xlsx
A71: Intl arrivals 2020 | B71: persons | C71: 6725000 | F71: https://www.nso.go.th/public/e-book/Indicators-Economic/Thai_Economic_Indicators_2025/158
A72: Intl tourism receipts 2025 mots | B72: THB bn | C72: 1587.208 | F72: https://www.mots.go.th/images/v2022_5a7fbad7-1fcf-4410-a387-f29bb17486e2.xlsx
A73: Intl tourism receipts 2024 mots | B73: THB bn | C73: 1612.603 | F73: https://www.mots.go.th/images/v2022_c1331820-8936-4423-84cd-65278cebf658.xlsx
A74: Intl tourism receipts usd wdi 2019 | B74: US$ bn | C74: 59.81 | F74: World Bank API, indicator ST.INT.TVLR.CD (international tourism receipts for travel items), Thailand. https://api.worldbank.org/v2/country/THA/indicator/ST.INT.TVLR.CD?format=json&date=2015:2025&per_page=100
A75: Intl tourism receipts usd wdi 2020 | B75: US$ bn | C75: 14.198 | F75: World Bank API, indicator ST.INT.TVLR.CD (international tourism receipts for travel items), Thailand. https://api.worldbank.org/v2/country/THA/indicator/ST.INT.TVLR.CD?format=json&date=2015:2025&per_page=100
A76: Intl tourism receipts bot thb bn 2019 2025 | B76: THB bn | C76: 1400 | F76: No external source located
A77: Ticket price ocean park adult hkd | B77: HK$ per adult admission | C77: 498 | F77: Australasian Leisure Management, Ocean Park entrance prices (2019), https://www.ausleisure.com.au/news/entrance-prices-at-hong-kongs-ocean-park-rise-by-4
A78: Ticket price universal studios singapore adult sgd | B78: SGD per adult ticket | C78: 76 | F78: https://www.rwsentosa.com/en/play/universal-studios-singapore/tickets
A79: Tsa attraction recreation spending share 2022 | B79: percent of visitor spending on attractions or recreation | F79: No external source located
A80: Hk disneyland attendance fy2019 | B80: million visitors | C80: 6.5 | F80: https://hkcorporate.hongkongdisneyland.com/pdf/AnnualBusinessReview19.pdf
A81: Hk disneyland attendance fy2024 | B81: million visitors | C81: 7.7 | F81: https://hkcorporate.hongkongdisneyland.com/pdf/AnnualBusinessReview24.pdf
A82: Hk disneyland attendance fy2025 | B82: million visitors | C82: 7.5 | F82: https://news.hongkongdisneyland.com/en/press/2026-04-28/
A83: Hk disneyland revenue fy2025 hkd m | B83: HK$ million | C83: 8694 | F83: https://hkcorporate.hongkongdisneyland.com/pdf/AnnualBusinessReview25.pdf
A84: Hk disneyland net profit fy2025 hkd m | B84: HK$ million | C84: 536 | F84: https://hkcorporate.hongkongdisneyland.com/pdf/AnnualBusinessReview25.pdf
A85: Hk disneyland adult ticket tier1 hkd | B85: HK$ per adult ticket | C85: 669 | F85: https://www.hongkongdisneyland.com/offers-discounts/travel-industry-salute/
A86: Hk disneyland adult ticket tier4 peak hkd | B86: HK$ per adult ticket | C86: 939 | F86: https://www.hongkongdisneyland.com/offers-discounts/travel-industry-salute/
A87: Hk disneyland visitor share local fy2019 | B87: percent of attendance | C87: 41 | F87: https://hkcorporate.hongkongdisneyland.com/pdf/AnnualBusinessReview19.pdf
A88: Hk disneyland visitor share mainland fy2019 | B88: percent of attendance | C88: 33 | F88: https://hkcorporate.hongkongdisneyland.com/pdf/AnnualBusinessReview19.pdf
A89: Hk disneyland visitor share other fy2019 | B89: percent of attendance | C89: 26 | F89: https://hkcorporate.hongkongdisneyland.com/pdf/AnnualBusinessReview19.pdf
A90: Ocean park attendance fy2024 25 | B90: million visitors | C90: 3.46 | F90: https://corporate.oceanpark.com.hk/en/media-partnerships/press-release/
A91: Ocean park non local visitors fy2024 25 | B91: million visitors | C91: 1.25 | F91: https://corporate.oceanpark.com.hk/en/media-partnerships/press-release/
... A98: Ocean park adult admission 2019 hkd | B98: HK$ per adult ticket | C98: 498 | F98: No external source located
A99: Universal studios singapore attendance 2024 million | B99: million visitors | F99: No external source located
A100: Lotte world adult ticket 2026 krw | B100: KRW per adult ticket (full-day pass) | C100: 67000 | F100: SBS Biz, Lotte World to raise adult ticket price, article dated 17 March 2026, lead paragraph. https://biz.sbs.co.kr/amp/article/20000297877
A101: Lotte world visitors 2023 million | B101: million persons | C101: 5.193 | F101: https://know.tour.go.kr/ptourknow/tourgoInfoView19Re.do?seq=103270
A102: Lotte world visitors 2024 million | B102: million persons | C102: 5.257 | F102: https://know.tour.go.kr/stat/visitStatDis/rankingStat.do
A103: Shanghai disneyland attendance 2024 million | B103: million visitors | C103: 14.7 | F103: Shanghai Municipal Government news, Shanghai Disneyland secures global top 5 position with record attendance, 27 October 2025, body paragraph on attendance. https://english.shanghai.gov.cn/en-Latest-WhatsNew/20251027/63097f5dd6ff4d2dad7e736573ead8d6.html
A104: Shanghai disneyland attendance 2019 million | B104: million visitors | C104: 11.21 | F104: TEA and AECOM Theme Index 2019, Top 25 table, rank 10, https://blooloop.com/files/75972/tea-report-2019.pdf
A105: Thailand 10y government bond yield 2026 10 14 | B105: rate per year | C105: 0.0232 | F105: No external source located
A106: Corporate income tax rate standard | B106: rate of net profit | C106: 0.2 | F106: Revenue Department, corporate income tax, https://www.rd.go.th/english/6044.html
A107: Vat statutory rate | B107: rate | C107: 0.1 | F107: https://www.rd.go.th/english/37732.html
A108: Vat reduced rate 2026 2027 | B108: rate, including local tax | C108: 0.07 | F108: KPMG TaxNewsFlash, same article, first paragraph on Royal Decree No. 807. Temporary reduced rate for 1 October 2026 to 30 September 2027. It must be checked again after 30 September 2027.
A109: Adb economic horizon years low | B109: years | C109: 20 | F109: ADB (2017) Guidelines for the Economic Analysis of Projects, printed pages 47 to 48, paragraph 176. https://www.adb.org/sites/default/files/institutional-document/32256/economic-analysis-projects.pdf
A110: Adb economic horizon years high | B110: years | C110: 30 | F110: ADB (2017) Guidelines for the Economic Analysis of Projects, printed pages 47 to 48, paragraph 176. https://www.adb.org/sites/default/files/institutional-document/32256/economic-analysis-projects.pdf
A111: Adb dam railway operating years low | B111: years | C111: 20 | F111: ADB (2017), printed page 64, Appendix 3, paragraph 2. https://www.adb.org/sites/default/files/institutional-document/32256/economic-analysis-projects.pdf
... A139: Cbre pattaya occupancy h2 2025 | B139: share | C139: 0.655 | F139: CBRE, Pattaya Overall Figures H2 2025. https://mktgdocs.cbre.com/2299/175bc843-73b5-4940-a859-14bd0f57a6a1-1295998069/Pattaya-Overall-Figures-H2-202.pdf
A140: Project life years | B140: years | C140: 20 | D140: 20 | E140: 25 | F140: NESDC Requirement
A141: Construction years | B141: years | C141: 2 | D141: 3 | E141: 2 | F141: ADB (2017) Guidelines, Appendix 3 illustrative implementation period, https://www.adb.org/sites/default/files/institutional-document/32256/economic-analysis-projects.pdf
A142: Wacc financial | B142: rate | C142: 0.08 | D142: 0.1 | E142: 0.07 | F142: NESDC Requirement
A143: Attendance million per year | B143: million visits per year | C143: 7.5 | D143: 3.46 | E143: 14.7 | F143: NESDC Assumption
A144: International share | B144: share of attendance | C144: 0.59 | D144: 0.36 | E144: 0.75 | F144: Hong Kong Disneyland Annual Business Review FY2019, origin of visitors, https://hkcorporate.hongkongdisneyland.com/pdf/AnnualBusinessReview19.pdf
A145: Incremental share | B145: share | C145: 0.3 | D145: 0.1 | E145: 0.5 | F145: NESDC Assumption
A146: Displacement share | B146: share | C146: 0.3 | D146: 0.5 | E146: 0.1 | F146: NESDC Assumption
A147: Spend per visit thb | B147: THB per incremental visit | C147: 10000 | D147: 1862 | E147: 20000 | F147: NESDC Assumption (base and high); Oriental Land Co., Tokyo Disney Resort FY3/2026, on-site spending per guest (low)
A148: Domestic retention share | B148: share | C148: 0.5 | D148: 0.3 | E148: 0.7 | F148: NESDC Assumption
A149: Tax share of spend | B149: share of net spending | C149: 0.065421 | D149: 0 | E149: 0.090909 | F149: NESDC Assumption; VAT rate, Revenue Department, https://www.rd.go.th/english/37732.html
A150: Opex share | B150: ratio of revenue | C150: 0.9383 | D150: 1.2146 | E150: 0.7 | F150: Hong Kong Disneyland Annual Business Review FY2025, https://hkcorporate.hongkongdisneyland.com/pdf/AnnualBusinessReview25.pdf
A151: Ticket revenue per visit thb | B151: THB per visit | C151: 2877 | D151: 2158 | E151: 4038 | F151: Hong Kong Disneyland adult ticket tier 1, https://www.hongkongdisneyland.com/offers-discounts/travel-industry-salute/
... A160: Occupancy ceiling serving site | B160: share | C160: 0.85 | D160: 0.8042 | E160: 0.9 | F160: NESDC Assumption
A162: Park-only operator inputs
A163: Park-only capital cost | B163: THB bn | C163: =C2 -> 200 | F163: Nation Thailand, 12 February 2026, https://www.nationthailand.com/blogs/business/investment/40062428
A164: Replacement capex, share of capital per operating year | B164: share | C164: 0 | F164: NESDC Assumption
A165: Hong Kong depreciation share of noncurrent assets | B165: share per year | C165: =C133/C134 -> 0.079093281 | F165: Hong Kong Disneyland Annual Business Review FY2025, https://hkcorporate.hongkongdisneyland.com/pdf/AnnualBusinessReview25.pdf
A166: Corporate income tax rate | B166: ratio | C166: =C106 -> 0.2 | F166: Revenue Department, corporate income tax, https://www.rd.go.th/english/6044.html
A167: Tax depreciation years | B167: years | C167: =C126 -> 20 | F167: NESDC Assumption

Sheet Appraisal
A1: Park-only operator financial appraisal (THB billion unless stated)
A4: Parameter | B4: Park-only
A5: Cash operating cost, share of revenue | B5: =Inputs!$C$132/Inputs!$C$83 -> 0.77122153
A6: WACC | B6: =Inputs!$C$142 -> 0.08
A7: Operating life (years) | B7: =Inputs!$C$140 -> 20
A8: Construction years | B8: =Inputs!$C$141 -> 2
A9: Capital cost (THB bn) | B9: =Inputs!$C$163 -> 200
A10: Attendance (million visits a year) | B10: =Inputs!$C$143 -> 7.5
A11: International share of attendance | B11: =Inputs!$C$144 -> 0.59
A12: Physical visit cap (million visits a year) | B12: =MIN(Inputs!$C$25/Inputs!$C$154,Inputs!$C$158*365*Inputs!$C$153/Inputs!$C$152)/1000000 -> 1.85
A13: Ticket revenue per visit (THB) | B13: =Inputs!$C$151 -> 2877
A14: Operator visits per operating year (million) | B14: =B10-MAX(B10*B11-B12,0) -> 4.925
A15: Operator revenue per operating year (THB bn) | B15: =B14*(B13+B19*Inputs!$D$147)/1000 -> 23.339575
A16: Replacement capex, share of capital per operating year | B16: =Inputs!$C$164 -> 0
A17: Corporate income tax rate | B17: =Inputs!$C$166 -> 0.2
A18: Tax depreciation years | B18: =Inputs!$C$167 -> 20
A19: On-site income included (1 = yes) | B19: 1
A20: Results | B20: Park-only
A21: Operator NPV before tax at WACC (THB bn) | B21: =SUM(K41:K85) -> -144.05102
A22: Operator NPV after tax (THB bn) | B22: =IF($B$18<$B$7,"n/a",SUM(R41:R85)) -> -144.05102
A23: Operator IRR after tax | B23: =IF($B$18<$B$7,"n/a",IRR(Q41:Q85,-0.1)) -> -0.05150944
A24: Break-even capital cost (THB bn) | B24: =B15*(1-B5)*B27/(B16*B27+B28/B9) -> 50.408561
A25: Break-even attendance (million visits a year) | B25: =B10-B21/((1-B5)*(B13+B19*Inputs!$D$147)/1000*(1-B11)*B27) -> 43.14715
A27: Annuity factor over operating years | B27: =SUMPRODUCT(B41:B85,D41:D85) -> 9.0908772
A28: Present value of capital cost (THB bn) | B28: =SUMPRODUCT(E41:E85,B41:B85) -> 192.59259
A31: Ledger covers the operating life | B31: =IF($B$8+$B$7-1<=MAX($A$41:$A$85),"Yes","No") -> Yes
A32: Tax depreciation covers the operating life | B32: =IF(B18<B7,"No","Yes") -> Yes
A33: Cumulative cash flow over the operating life, before tax (THB bn) | B33: =SUM(J41:J85) -> -93.208156
A34: Years of operation needed for nominal payback | B34: =IF(B15*(1-B5)-B16*B9<=0,"never",B9/(B15*(1-B5)-B16*B9)) -> 37.456044
A35: Estimated nominal payback year (from start of construction) | B35: =IF(ISNUMBER(B34),B8+B34,"never") -> 39.456044
A36: Nominal payback within the operating life | B36: =IF(ISNUMBER(B34),IF(B34<=B7,"Yes","No"),"No") -> No
A37: Estimated discounted payback year at WACC (from start of construction) | B37: =IF(B15*(1-B5)-B16*B9<=0,"never",IF(B28*B6*(1+B6)^(B8-1)/(B15*(1-B5)-B16*B9)>=1,"never",B8-LN(1-B28*B6*(1+B6)^(B8-1)/(B15*(1-B5)-B16*B9))/LN(1+B6))) -> never
A39: Annual ledger, park-only
A40: Year | B40: Discount factor | C40: Construction | D40: Operating | E40: Capital cost | F40: Operator visits (million) | G40: Revenue | H40: Cash operating cost | I40: Replacement capex | J40: Cash flow before tax | K40: Present value before tax | L40: Tax depreciation | M40: Taxable income | N40: Cumulative taxable income | O40: Cumulative tax due | P40: Tax paid | Q40: Cash flow after tax | R40: Present value after tax | S40: Cumulative cash flow after tax | U40: Capital outflow, absolute (THB bn) | V40: Operating cash flow (THB bn)
A41: 0 | B41: =1/(1+$B$6)^A41 -> 1 | C41: =IF(A41<$B$8,1,0) -> 1 | D41: =IF(AND(A41>=$B$8,A41<$B$8+$B$7),1,0) -> 0 | E41: =C41*$B$9/$B$8 -> 100 | F41: =D41*$B$14 -> 0 | G41: =F41*($B$13+$B$19*Inputs!$D$147)/1000 -> 0 | H41: =$B$5*G41 -> 0 | I41: =D41*$B$16*$B$9 -> 0 | J41: =G41-H41-E41-I41 -> -100 | K41: =J41*B41 -> -100 | L41: =IF(AND(A41>=$B$8,A41<$B$8+$B$18),$B$9/$B$18,0) -> 0 | M41: =G41-H41-L41 -> 0 | N41: =SUM($M$41:M41) -> 0 | O41: =$B$17*MAX(0,N41) -> 0 | P41: =MAX(0,O41) -> 0 | Q41: =J41-P41 -> -100 | R41: =Q41*B41 -> -100 | S41: =SUM($Q$41:Q41) -> -100 | U41: =IF(J41<0,-J41,NA()) -> 100 | V41: =IF(J41>0,J41,NA()) -> #N/A
A42: 1 | B42: =1/(1+$B$6)^A42 -> 0.92592593 | C42: =IF(A42<$B$8,1,0) -> 1 | D42: =IF(AND(A42>=$B$8,A42<$B$8+$B$7),1,0) -> 0 | E42: =C42*$B$9/$B$8 -> 100 | F42: =D42*$B$14 -> 0 | G42: =F42*($B$13+$B$19*Inputs!$D$147)/1000 -> 0 | H42: =$B$5*G42 -> 0 | I42: =D42*$B$16*$B$9 -> 0 | J42: =G42-H42-E42-I42 -> -100 | K42: =J42*B42 -> -92.592593 | L42: =IF(AND(A42>=$B$8,A42<$B$8+$B$18),$B$9/$B$18,0) -> 0 | M42: =G42-H42-L42 -> 0 | N42: =SUM($M$41:M42) -> 0 | O42: =$B$17*MAX(0,N42) -> 0 | P42: =MAX(0,O42-O41) -> 0 | Q42: =J42-P42 -> -100 | R42: =Q42*B42 -> -92.592593 | S42: =SUM($Q$41:Q42) -> -200 | U42: =IF(J42<0,-J42,NA()) -> 100 | V42: =IF(J42>0,J42,NA()) -> #N/A
A43: 2 | B43: =1/(1+$B$6)^A43 -> 0.85733882 | C43: =IF(A43<$B$8,1,0) -> 0 | D43: =IF(AND(A43>=$B$8,A43<$B$8+$B$7),1,0) -> 1 | E43: =C43*$B$9/$B$8 -> 0 | F43: =D43*$B$14 -> 4.925 | G43: =F43*($B$13+$B$19*Inputs!$D$147)/1000 -> 23.339575 | H43: =$B$5*G43 -> 17.999983 | I43: =D43*$B$16*$B$9 -> 0 | J43: =G43-H43-E43-I43 -> 5.3395922 | K43: =J43*B43 -> 4.5778397 | L43: =IF(AND(A43>=$B$8,A43<$B$8+$B$18),$B$9/$B$18,0) -> 10 | M43: =G43-H43-L43 -> -4.6604078 | N43: =SUM($M$41:M43) -> -4.6604078 | O43: =$B$17*MAX(0,N43) -> 0 | P43: =MAX(0,O43-O42) -> 0 | Q43: =J43-P43 -> 5.3395922 | R43: =Q43*B43 -> 4.5778397 | S43: =SUM($Q$41:Q43) -> -194.66041 | U43: =IF(J43<0,-J43,NA()) -> #N/A | V43: =IF(J43>0,J43,NA()) -> 5.3395922
A44: 3 | B44: =1/(1+$B$6)^A44 -> 0.79383224 | C44: =IF(A44<$B$8,1,0) -> 0 | D44: =IF(AND(A44>=$B$8,A44<$B$8+$B$7),1,0) -> 1 | E44: =C44*$B$9/$B$8 -> 0 | F44: =D44*$B$14 -> 4.925 | G44: =F44*($B$13+$B$19*Inputs!$D$147)/1000 -> 23.339575 | H44: =$B$5*G44 -> 17.999983 | I44: =D44*$B$16*$B$9 -> 0 | J44: =G44-H44-E44-I44 -> 5.3395922 | K44: =J44*B44 -> 4.2387405 | L44: =IF(AND(A44>=$B$8,A44<$B$8+$B$18),$B$9/$B$18,0) -> 10 | M44: =G44-H44-L44 -> -4.6604078 | N44: =SUM($M$41:M44) -> -9.3208156 | O44: =$B$17*MAX(0,N44) -> 0 | P44: =MAX(0,O44-O43) -> 0 | Q44: =J44-P44 -> 5.3395922 | R44: =Q44*B44 -> 4.2387405 | S44: =SUM($Q$41:Q44) -> -189.32082 | U44: =IF(J44<0,-J44,NA()) -> #N/A | V44: =IF(J44>0,J44,NA()) -> 5.3395922
A45: 4 | B45: =1/(1+$B$6)^A45 -> 0.73502985 | C45: =IF(A45<$B$8,1,0) -> 0 | D45: =IF(AND(A45>=$B$8,A45<$B$8+$B$7),1,0) -> 1 | E45: =C45*$B$9/$B$8 -> 0 | F45: =D45*$B$14 -> 4.925 | G45: =F45*($B$13+$B$19*Inputs!$D$147)/1000 -> 23.339575 | H45: =$B$5*G45 -> 17.999983 | I45: =D45*$B$16*$B$9 -> 0 | J45: =G45-H45-E45-I45 -> 5.3395922 | K45: =J45*B45 -> 3.9247597 | L45: =IF(AND(A45>=$B$8,A45<$B$8+$B$18),$B$9/$B$18,0) -> 10 | M45: =G45-H45-L45 -> -4.6604078 | N45: =SUM($M$41:M45) -> -13.981223 | O45: =$B$17*MAX(0,N45) -> 0 | P45: =MAX(0,O45-O44) -> 0 | Q45: =J45-P45 -> 5.3395922 | R45: =Q45*B45 -> 3.9247597 | S45: =SUM($Q$41:Q45) -> -183.98122 | U45: =IF(J45<0,-J45,NA()) -> #N/A | V45: =IF(J45>0,J45,NA()) -> 5.3395922
A46: 5 | B46: =1/(1+$B$6)^A46 -> 0.6805832 | C46: =IF(A46<$B$8,1,0) -> 0 | D46: =IF(AND(A46>=$B$8,A46<$B$8+$B$7),1,0) -> 1 | E46: =C46*$B$9/$B$8 -> 0 | F46: =D46*$B$14 -> 4.925 | G46: =F46*($B$13+$B$19*Inputs!$D$147)/1000 -> 23.339575 | H46: =$B$5*G46 -> 17.999983 | I46: =D46*$B$16*$B$9 -> 0 | J46: =G46-H46-E46-I46 -> 5.3395922 | K46: =J46*B46 -> 3.6340367 | L46: =IF(AND(A46>=$B$8,A46<$B$8+$B$18),$B$9/$B$18,0) -> 10 | M46: =G46-H46-L46 -> -4.6604078 | N46: =SUM($M$41:M46) -> -18.641631 | O46: =$B$17*MAX(0,N46) -> 0 | P46: =MAX(0,O46-O45) -> 0 | Q46: =J46-P46 -> 5.3395922 | R46: =Q46*B46 -> 3.6340367 | S46: =SUM($Q$41:Q46) -> -178.64163 | U46: =IF(J46<0,-J46,NA()) -> #N/A | V46: =IF(J46>0,J46,NA()) -> 5.3395922
A47: 6 | B47: =1/(1+$B$6)^A47 -> 0.63016963 | C47: =IF(A47<$B$8,1,0) -> 0 | D47: =IF(AND(A47>=$B$8,A47<$B$8+$B$7),1,0) -> 1 | E47: =C47*$B$9/$B$8 -> 0 | F47: =D47*$B$14 -> 4.925 | G47: =F47*($B$13+$B$19*Inputs!$D$147)/1000 -> 23.339575 | H47: =$B$5*G47 -> 17.999983 | I47: =D47*$B$16*$B$9 -> 0 | J47: =G47-H47-E47-I47 -> 5.3395922 | K47: =J47*B47 -> 3.3648488 | L47: =IF(AND(A47>=$B$8,A47<$B$8+$B$18),$B$9/$B$18,0) -> 10 | M47: =G47-H47-L47 -> -4.6604078 | N47: =SUM($M$41:M47) -> -23.302039 | O47: =$B$17*MAX(0,N47) -> 0 | P47: =MAX(0,O47-O46) -> 0 | Q47: =J47-P47 -> 5.3395922 | R47: =Q47*B47 -> 3.3648488 | S47: =SUM($Q$41:Q47) -> -173.30204 | U47: =IF(J47<0,-J47,NA()) -> #N/A | V47: =IF(J47>0,J47,NA()) -> 5.3395922
A48: 7 | B48: =1/(1+$B$6)^A48 -> 0.5834904 | C48: =IF(A48<$B$8,1,0) -> 0 | D48: =IF(AND(A48>=$B$8,A48<$B$8+$B$7),1,0) -> 1 | E48: =C48*$B$9/$B$8 -> 0 | F48: =D48*$B$14 -> 4.925 | G48: =F48*($B$13+$B$19*Inputs!$D$147)/1000 -> 23.339575 | H48: =$B$5*G48 -> 17.999983 | I48: =D48*$B$16*$B$9 -> 0 | J48: =G48-H48-E48-I48 -> 5.3395922 | K48: =J48*B48 -> 3.1156008 | L48: =IF(AND(A48>=$B$8,A48<$B$8+$B$18),$B$9/$B$18,0) -> 10 | M48: =G48-H48-L48 -> -4.6604078 | N48: =SUM($M$41:M48) -> -27.962447 | O48: =$B$17*MAX(0,N48) -> 0 | P48: =MAX(0,O48-O47) -> 0 | Q48: =J48-P48 -> 5.3395922 | R48: =Q48*B48 -> 3.1156008 | S48: =SUM($Q$41:Q48) -> -167.96245 | U48: =IF(J48<0,-J48,NA()) -> #N/A | V48: =IF(J48>0,J48,NA()) -> 5.3395922
A49: 8 | B49: =1/(1+$B$6)^A49 -> 0.54026888 | C49: =IF(A49<$B$8,1,0) -> 0 | D49: =IF(AND(A49>=$B$8,A49<$B$8+$B$7),1,0) -> 1 | E49: =C49*$B$9/$B$8 -> 0 | F49: =D49*$B$14 -> 4.925 | G49: =F49*($B$13+$B$19*Inputs!$D$147)/1000 -> 23.339575 | H49: =$B$5*G49 -> 17.999983 | I49: =D49*$B$16*$B$9 -> 0 | J49: =G49-H49-E49-I49 -> 5.3395922 | K49: =J49*B49 -> 2.8848155 | L49: =IF(AND(A49>=$B$8,A49<$B$8+$B$18),$B$9/$B$18,0) -> 10 | M49: =G49-H49-L49 -> -4.6604078 | N49: =SUM($M$41:M49) -> -32.622855 | O49: =$B$17*MAX(0,N49) -> 0 | P49: =MAX(0,O49-O48) -> 0 | Q49: =J49-P49 -> 5.3395922 | R49: =Q49*B49 -> 2.8848155 | S49: =SUM($Q$41:Q49) -> -162.62285 | U49: =IF(J49<0,-J49,NA()) -> #N/A | V49: =IF(J49>0,J49,NA()) -> 5.3395922
A50: 9 | B50: =1/(1+$B$6)^A50 -> 0.50024897 | C50: =IF(A50<$B$8,1,0) -> 0 | D50: =IF(AND(A50>=$B$8,A50<$B$8+$B$7),1,0) -> 1 | E50: =C50*$B$9/$B$8 -> 0 | F50: =D50*$B$14 -> 4.925 | G50: =F50*($B$13+$B$19*Inputs!$D$147)/1000 -> 23.339575 | H50: =$B$5*G50 -> 17.999983 | I50: =D50*$B$16*$B$9 -> 0 | J50: =G50-H50-E50-I50 -> 5.3395922 | K50: =J50*B50 -> 2.6711255 | L50: =IF(AND(A50>=$B$8,A50<$B$8+$B$18),$B$9/$B$18,0) -> 10 | M50: =G50-H50-L50 -> -4.6604078 | N50: =SUM($M$41:M50) -> -37.283262 | O50: =$B$17*MAX(0,N50) -> 0 | P50: =MAX(0,O50-O49) -> 0 | Q50: =J50-P50 -> 5.3395922 | R50: =Q50*B50 -> 2.6711255 | S50: =SUM($Q$41:Q50) -> -157.28326 | U50: =IF(J50<0,-J50,NA()) -> #N/A | V50: =IF(J50>0,J50,NA()) -> 5.3395922
A51: 10 | B51: =1/(1+$B$6)^A51 -> 0.46319349 | C51: =IF(A51<$B$8,1,0) -> 0 | D51: =IF(AND(A51>=$B$8,A51<$B$8+$B$7),1,0) -> 1 | E51: =C51*$B$9/$B$8 -> 0 | F51: =D51*$B$14 -> 4.925 | G51: =F51*($B$13+$B$19*Inputs!$D$147)/1000 -> 23.339575 | H51: =$B$5*G51 -> 17.999983 | I51: =D51*$B$16*$B$9 -> 0 | J51: =G51-H51-E51-I51 -> 5.3395922 | K51: =J51*B51 -> 2.4732643 | L51: =IF(AND(A51>=$B$8,A51<$B$8+$B$18),$B$9/$B$18,0) -> 10 | M51: =G51-H51-L51 -> -4.6604078 | N51: =SUM($M$41:M51) -> -41.94367 | O51: =$B$17*MAX(0,N51) -> 0 | P51: =MAX(0,O51-O50) -> 0 | Q51: =J51-P51 -> 5.3395922 | R51: =Q51*B51 -> 2.4732643 | S51: =SUM($Q$41:Q51) -> -151.94367 | U51: =IF(J51<0,-J51,NA()) -> #N/A | V51: =IF(J51>0,J51,NA()) -> 5.3395922
A52: 11 | B52: =1/(1+$B$6)^A52 -> 0.42888286 | C52: =IF(A52<$B$8,1,0) -> 0 | D52: =IF(AND(A52>=$B$8,A52<$B$8+$B$7),1,0) -> 1 | E52: =C52*$B$9/$B$8 -> 0 | F52: =D52*$B$14 -> 4.925 | G52: =F52*($B$13+$B$19*Inputs!$D$147)/1000 -> 23.339575 | H52: =$B$5*G52 -> 17.999983 | I52: =D52*$B$16*$B$9 -> 0 | J52: =G52-H52-E52-I52 -> 5.3395922 | K52: =J52*B52 -> 2.2900596 | L52: =IF(AND(A52>=$B$8,A52<$B$8+$B$18),$B$9/$B$18,0) -> 10 | M52: =G52-H52-L52 -> -4.6604078 | N52: =SUM($M$41:M52) -> -46.604078 | O52: =$B$17*MAX(0,N52) -> 0 | P52: =MAX(0,O52-O51) -> 0 | Q52: =J52-P52 -> 5.3395922 | R52: =Q52*B52 -> 2.2900596 | S52: =SUM($Q$41:Q52) -> -146.60408 | U52: =IF(J52<0,-J52,NA()) -> #N/A | V52: =IF(J52>0,J52,NA()) -> 5.3395922
A53: 12 | B53: =1/(1+$B$6)^A53 -> 0.39711376 | C53: =IF(A53<$B$8,1,0) -> 0 | D53: =IF(AND(A53>=$B$8,A53<$B$8+$B$7),1,0) -> 1 | E53: =C53*$B$9/$B$8 -> 0 | F53: =D53*$B$14 -> 4.925 | G53: =F53*($B$13+$B$19*Inputs!$D$147)/1000 -> 23.339575 | H53: =$B$5*G53 -> 17.999983 | I53: =D53*$B$16*$B$9 -> 0 | J53: =G53-H53-E53-I53 -> 5.3395922 | K53: =J53*B53 -> 2.1204255 | L53: =IF(AND(A53>=$B$8,A53<$B$8+$B$18),$B$9/$B$18,0) -> 10 | M53: =G53-H53-L53 -> -4.6604078 | N53: =SUM($M$41:M53) -> -51.264486 | O53: =$B$17*MAX(0,N53) -> 0 | P53: =MAX(0,O53-O52) -> 0 | Q53: =J53-P53 -> 5.3395922 | R53: =Q53*B53 -> 2.1204255 | S53: =SUM($Q$41:Q53) -> -141.26449 | U53: =IF(J53<0,-J53,NA()) -> #N/A | V53: =IF(J53>0,J53,NA()) -> 5.3395922
... A85: 44 | B85: =1/(1+$B$6)^A85 -> 0.03383411 | C85: =IF(A85<$B$8,1,0) -> 0 | D85: =IF(AND(A85>=$B$8,A85<$B$8+$B$7),1,0) -> 0 | E85: =C85*$B$9/$B$8 -> 0 | F85: =D85*$B$14 -> 0 | G85: =F85*($B$13+$B$19*Inputs!$D$147)/1000 -> 0 | H85: =$B$5*G85 -> 0 | I85: =D85*$B$16*$B$9 -> 0 | J85: =G85-H85-E85-I85 -> 0 | K85: =J85*B85 -> 0 | L85: =IF(AND(A85>=$B$8,A85<$B$8+$B$18),$B$9/$B$18,0) -> 0 | M85: =G85-H85-L85 -> 0 | N85: =SUM($M$41:M85) -> -93.208156 | O85: =$B$17*MAX(0,N85) -> 0 | P85: =MAX(0,O85-O84) -> 0 | Q85: =J85-P85 -> 0 | R85: =Q85*B85 -> 0 | S85: =SUM($Q$41:Q85) -> -93.208156 | U85: =IF(J85<0,-J85,NA()) -> #N/A | V85: =IF(J85>0,J85,NA()) -> #N/A
A88: Sensitivity cases
A89: Case | B89: Capital cost factor | C89: Opex factor | D89: Revenue factor | E89: Opening delay (years) | F89: Annuity factor | G89: NPV before tax, park-only | H89: Replacement share | I89: Taxable income, park-only | J89: NPV after tax, park-only | K89: Chart label
A90: Base | B90: 1 | C90: 1 | D90: 1 | E90: 0 | F90: =SUMPRODUCT($B$41:$B$85*($A$41:$A$85>=$B$8+E90)*($A$41:$A$85<$B$8+E90+$B$7)) -> 9.0908772 | G90: =(D90-C90*$B$5)*$B$15*F90-B90*$B$28-H90*B90*$B$9*F90 -> -144.05102 | H90: =$B$16 -> 0 | I90: =D90*$B$15-C90*$B$5*$B$15-B90*$B$9/$B$18 -> -4.6604078 | J90: =IF($B$18<$B$7,"n/a",G90-$B$17*MAX(0,I90)*F90) -> -144.05102 | K90: Base
A91: Construction cost +5% | B91: 1.05 | C91: 1 | D91: 1 | E91: 0 | F91: =SUMPRODUCT($B$41:$B$85*($A$41:$A$85>=$B$8+E91)*($A$41:$A$85<$B$8+E91+$B$7)) -> 9.0908772 | G91: =(D91-C91*$B$5)*$B$15*F91-B91*$B$28-H91*B91*$B$9*F91 -> -153.68064 | H91: =$B$16 -> 0 | I91: =D91*$B$15-C91*$B$5*$B$15-B91*$B$9/$B$18 -> -5.1604078 | J91: =IF($B$18<$B$7,"n/a",G91-$B$17*MAX(0,I91)*F91) -> -153.68064 | K91: Construction cost +5%
A92: Construction cost -5% | B92: 0.95 | C92: 1 | D92: 1 | E92: 0 | F92: =SUMPRODUCT($B$41:$B$85*($A$41:$A$85>=$B$8+E92)*($A$41:$A$85<$B$8+E92+$B$7)) -> 9.0908772 | G92: =(D92-C92*$B$5)*$B$15*F92-B92*$B$28-H92*B92*$B$9*F92 -> -134.42139 | H92: =$B$16 -> 0 | I92: =D92*$B$15-C92*$B$5*$B$15-B92*$B$9/$B$18 -> -4.1604078 | J92: =IF($B$18<$B$7,"n/a",G92-$B$17*MAX(0,I92)*F92) -> -134.42139 | K92: Construction cost -5%
A93: Construction cost +10% | B93: 1.1 | C93: 1 | D93: 1 | E93: 0 | F93: =SUMPRODUCT($B$41:$B$85*($A$41:$A$85>=$B$8+E93)*($A$41:$A$85<$B$8+E93+$B$7)) -> 9.0908772 | G93: =(D93-C93*$B$5)*$B$15*F93-B93*$B$28-H93*B93*$B$9*F93 -> -163.31027 | H93: =$B$16 -> 0 | I93: =D93*$B$15-C93*$B$5*$B$15-B93*$B$9/$B$18 -> -5.6604078 | J93: =IF($B$18<$B$7,"n/a",G93-$B$17*MAX(0,I93)*F93) -> -163.31027 | K93: Construction cost +10%
A94: Construction cost -10% | B94: 0.9 | C94: 1 | D94: 1 | E94: 0 | F94: =SUMPRODUCT($B$41:$B$85*($A$41:$A$85>=$B$8+E94)*($A$41:$A$85<$B$8+E94+$B$7)) -> 9.0908772 | G94: =(D94-C94*$B$5)*$B$15*F94-B94*$B$28-H94*B94*$B$9*F94 -> -124.79176 | H94: =$B$16 -> 0 | I94: =D94*$B$15-C94*$B$5*$B$15-B94*$B$9/$B$18 -> -3.6604078 | J94: =IF($B$18<$B$7,"n/a",G94-$B$17*MAX(0,I94)*F94) -> -124.79176 | K94: Construction cost -10%
A95: Construction cost +20% | B95: 1.2 | C95: 1 | D95: 1 | E95: 0 | F95: =SUMPRODUCT($B$41:$B$85*($A$41:$A$85>=$B$8+E95)*($A$41:$A$85<$B$8+E95+$B$7)) -> 9.0908772 | G95: =(D95-C95*$B$5)*$B$15*F95-B95*$B$28-H95*B95*$B$9*F95 -> -182.56953 | H95: =$B$16 -> 0 | I95: =D95*$B$15-C95*$B$5*$B$15-B95*$B$9/$B$18 -> -6.6604078 | J95: =IF($B$18<$B$7,"n/a",G95-$B$17*MAX(0,I95)*F95) -> -182.56953 | K95: Construction cost +20%
A96: Construction cost -20% | B96: 0.8 | C96: 1 | D96: 1 | E96: 0 | F96: =SUMPRODUCT($B$41:$B$85*($A$41:$A$85>=$B$8+E96)*($A$41:$A$85<$B$8+E96+$B$7)) -> 9.0908772 | G96: =(D96-C96*$B$5)*$B$15*F96-B96*$B$28-H96*B96*$B$9*F96 -> -105.5325 | H96: =$B$16 -> 0 | I96: =D96*$B$15-C96*$B$5*$B$15-B96*$B$9/$B$18 -> -2.6604078 | J96: =IF($B$18<$B$7,"n/a",G96-$B$17*MAX(0,I96)*F96) -> -105.5325 | K96: Construction cost -20%
A97: Operating cost +5% | B97: 1 | C97: 1.05 | D97: 1 | E97: 0 | F97: =SUMPRODUCT($B$41:$B$85*($A$41:$A$85>=$B$8+E97)*($A$41:$A$85<$B$8+E97+$B$7)) -> 9.0908772 | G97: =(D97-C97*$B$5)*$B$15*F97-B97*$B$28-H97*B97*$B$9*F97 -> -152.2328 | H97: =$B$16 -> 0 | I97: =D97*$B$15-C97*$B$5*$B$15-B97*$B$9/$B$18 -> -5.5604069 | J97: =IF($B$18<$B$7,"n/a",G97-$B$17*MAX(0,I97)*F97) -> -152.2328 | K97: Operating cost +5%
A98: Operating cost -5% | B98: 1 | C98: 0.95 | D98: 1 | E98: 0 | F98: =SUMPRODUCT($B$41:$B$85*($A$41:$A$85>=$B$8+E98)*($A$41:$A$85<$B$8+E98+$B$7)) -> 9.0908772 | G98: =(D98-C98*$B$5)*$B$15*F98-B98*$B$28-H98*B98*$B$9*F98 -> -135.86923 | H98: =$B$16 -> 0 | I98: =D98*$B$15-C98*$B$5*$B$15-B98*$B$9/$B$18 -> -3.7604087 | J98: =IF($B$18<$B$7,"n/a",G98-$B$17*MAX(0,I98)*F98) -> -135.86923 | K98: Operating cost -5%
A99: Operating cost +10% | B99: 1 | C99: 1.1 | D99: 1 | E99: 0 | F99: =SUMPRODUCT($B$41:$B$85*($A$41:$A$85>=$B$8+E99)*($A$41:$A$85<$B$8+E99+$B$7)) -> 9.0908772 | G99: =(D99-C99*$B$5)*$B$15*F99-B99*$B$28-H99*B99*$B$9*F99 -> -160.41458 | H99: =$B$16 -> 0 | I99: =D99*$B$15-C99*$B$5*$B$15-B99*$B$9/$B$18 -> -6.4604061 | J99: =IF($B$18<$B$7,"n/a",G99-$B$17*MAX(0,I99)*F99) -> -160.41458 | K99: Operating cost +10%
A100: Operating cost -10% | B100: 1 | C100: 0.9 | D100: 1 | E100: 0 | F100: =SUMPRODUCT($B$41:$B$85*($A$41:$A$85>=$B$8+E100)*($A$41:$A$85<$B$8+E100+$B$7)) -> 9.0908772 | G100: =(D100-C100*$B$5)*$B$15*F100-B100*$B$28-H100*B100*$B$9*F100 -> -127.68745 | H100: =$B$16 -> 0 | I100: =D100*$B$15-C100*$B$5*$B$15-B100*$B$9/$B$18 -> -2.8604095 | J100: =IF($B$18<$B$7,"n/a",G100-$B$17*MAX(0,I100)*F100) -> -127.68745 | K100: Operating cost -10%
A101: Operating cost +20% | B101: 1 | C101: 1.2 | D101: 1 | E101: 0 | F101: =SUMPRODUCT($B$41:$B$85*($A$41:$A$85>=$B$8+E101)*($A$41:$A$85<$B$8+E101+$B$7)) -> 9.0908772 | G101: =(D101-C101*$B$5)*$B$15*F101-B101*$B$28-H101*B101*$B$9*F101 -> -176.77814 | H101: =$B$16 -> 0 | I101: =D101*$B$15-C101*$B$5*$B$15-B101*$B$9/$B$18 -> -8.2604043 | J101: =IF($B$18<$B$7,"n/a",G101-$B$17*MAX(0,I101)*F101) -> -176.77814 | K101: Operating cost +20%
... A115: One-year opening delay | B115: 1 | C115: 1 | D115: 1 | E115: 1 | F115: =SUMPRODUCT($B$41:$B$85*($A$41:$A$85>=$B$8+E115)*($A$41:$A$85<$B$8+E115+$B$7)) -> 8.4174789 | G115: =(D115-C115*$B$5)*$B$15*F115-B115*$B$28-H115*B115*$B$9*F115 -> -147.64669 | H115: =$B$16 -> 0 | I115: =D115*$B$15-C115*$B$5*$B$15-B115*$B$9/$B$18 -> -4.6604078 | J115: =IF($B$18<$B$7,"n/a",G115-$B$17*MAX(0,I115)*F115) -> -147.64669 | K115: One-year opening delay
A116: Replacement at HK depreciation share | B116: 1 | C116: 1 | D116: 1 | E116: 0 | F116: =SUMPRODUCT($B$41:$B$85*($A$41:$A$85>=$B$8+E116)*($A$41:$A$85<$B$8+E116+$B$7)) -> 9.0908772 | G116: =(D116-C116*$B$5)*$B$15*F116-B116*$B$28-H116*B116*$B$9*F116 -> -287.85648 | H116: =Inputs!$C$165 -> 0.079093281 | I116: =D116*$B$15-C116*$B$5*$B$15-B116*$B$9/$B$18 -> -4.6604078 | J116: =IF($B$18<$B$7,"n/a",G116-$B$17*MAX(0,I116)*F116) -> -287.85648 | K116: Replacement at HK depreciation share
A123: Scenarios (NPV before tax, THB bn)
A124: Scenario | B124: WACC | C124: Operating life (years) | D124: On-site income (1 = yes) | E124: Replacement share | F124: Revenue (THB bn a year) | G124: Annuity factor | H124: Capital present value | I124: NPV before tax (THB bn)
A125: Park-only, ticket and on-site revenue | B125: =B6 -> 0.08 | C125: =B7 -> 20 | D125: =$B$19 -> 1 | E125: =B16 -> 0 | F125: =$B$14*$B$13/1000+D125*$B$14*Inputs!$D$147/1000 -> 23.339575 | G125: =(1+B125)^(-$B$8)*(1-(1+B125)^(-C125))/(1-1/(1+B125)) -> 9.0908772 | H125: =($B$9/$B$8)*(1-(1+B125)^(-$B$8))/(1-1/(1+B125)) -> 192.59259 | I125: =(F125*(1-$B$5)-E125*$B$9)*G125-H125 -> -144.05102
A126: Ticket revenue only | B126: =B6 -> 0.08 | C126: =B7 -> 20 | D126: 0 | E126: =B16 -> 0 | F126: =$B$14*$B$13/1000+D126*$B$14*Inputs!$D$147/1000 -> 14.169225 | G126: =(1+B126)^(-$B$8)*(1-(1+B126)^(-C126))/(1-1/(1+B126)) -> 9.0908772 | H126: =($B$9/$B$8)*(1-(1+B126)^(-$B$8))/(1-1/(1+B126)) -> 192.59259 | I126: =(F126*(1-$B$5)-E126*$B$9)*G126-H126 -> -163.12348
A127: Operating life 30 years | B127: =B6 -> 0.08 | C127: 30 | D127: =$B$19 -> 1 | E127: =B16 -> 0 | F127: =$B$14*$B$13/1000+D127*$B$14*Inputs!$D$147/1000 -> 23.339575 | G127: =(1+B127)^(-$B$8)*(1-(1+B127)^(-C127))/(1-1/(1+B127)) -> 10.423873 | H127: =($B$9/$B$8)*(1-(1+B127)^(-$B$8))/(1-1/(1+B127)) -> 192.59259 | I127: =(F127*(1-$B$5)-E127*$B$9)*G127-H127 -> -136.93336
A128: Operating life 40 years | B128: =B6 -> 0.08 | C128: 40 | D128: =$B$19 -> 1 | E128: =B16 -> 0 | F128: =$B$14*$B$13/1000+D128*$B$14*Inputs!$D$147/1000 -> 23.339575 | G128: =(1+B128)^(-$B$8)*(1-(1+B128)^(-C128))/(1-1/(1+B128)) -> 11.041309 | H128: =($B$9/$B$8)*(1-(1+B128)^(-$B$8))/(1-1/(1+B128)) -> 192.59259 | I128: =(F128*(1-$B$5)-E128*$B$9)*G128-H128 -> -133.63651
A129: WACC 6% | B129: 0.06 | C129: =B7 -> 20 | D129: =$B$19 -> 1 | E129: =B16 -> 0 | F129: =$B$14*$B$13/1000+D129*$B$14*Inputs!$D$147/1000 -> 23.339575 | G129: =(1+B129)^(-$B$8)*(1-(1+B129)^(-C129))/(1-1/(1+B129)) -> 10.82068 | H129: =($B$9/$B$8)*(1-(1+B129)^(-$B$8))/(1-1/(1+B129)) -> 194.33962 | I129: =(F129*(1-$B$5)-E129*$B$9)*G129-H129 -> -136.5616
A130: WACC 7% | B130: 0.07 | C130: =B7 -> 20 | D130: =$B$19 -> 1 | E130: =B16 -> 0 | F130: =$B$14*$B$13/1000+D130*$B$14*Inputs!$D$147/1000 -> 23.339575 | G130: =(1+B130)^(-$B$8)*(1-(1+B130)^(-C130))/(1-1/(1+B130)) -> 9.9009479 | H130: =($B$9/$B$8)*(1-(1+B130)^(-$B$8))/(1-1/(1+B130)) -> 193.45794 | I130: =(F130*(1-$B$5)-E130*$B$9)*G130-H130 -> -140.59092
A131: WACC 10% | B131: 0.1 | C131: =B7 -> 20 | D131: =$B$19 -> 1 | E131: =B16 -> 0 | F131: =$B$14*$B$13/1000+D131*$B$14*Inputs!$D$147/1000 -> 23.339575 | G131: =(1+B131)^(-$B$8)*(1-(1+B131)^(-C131))/(1-1/(1+B131)) -> 7.7396034 | H131: =($B$9/$B$8)*(1-(1+B131)^(-$B$8))/(1-1/(1+B131)) -> 190.90909 | I131: =(F131*(1-$B$5)-E131*$B$9)*G131-H131 -> -149.58276
A132: Replacement at Hong Kong depreciation share | B132: =B6 -> 0.08 | C132: =B7 -> 20 | D132: =$B$19 -> 1 | E132: =Inputs!$C$165 -> 0.079093281 | F132: =$B$14*$B$13/1000+D132*$B$14*Inputs!$D$147/1000 -> 23.339575 | G132: =(1+B132)^(-$B$8)*(1-(1+B132)^(-C132))/(1-1/(1+B132)) -> 9.0908772 | H132: =($B$9/$B$8)*(1-(1+B132)^(-$B$8))/(1-1/(1+B132)) -> 192.59259 | I132: =(F132*(1-$B$5)-E132*$B$9)*G132-H132 -> -287.85648
A133: Operating life 30 years, replacement at HK share | B133: =B6 -> 0.08 | C133: 30 | D133: =$B$19 -> 1 | E133: =Inputs!$C$165 -> 0.079093281 | F133: =$B$14*$B$13/1000+D133*$B$14*Inputs!$D$147/1000 -> 23.339575 | G133: =(1+B133)^(-$B$8)*(1-(1+B133)^(-C133))/(1-1/(1+B133)) -> 10.423873 | H133: =($B$9/$B$8)*(1-(1+B133)^(-$B$8))/(1-1/(1+B133)) -> 192.59259 | I133: =(F133*(1-$B$5)-E133*$B$9)*G133-H133 -> -301.82503
A134: Ticket revenue only, replacement at HK share | B134: =B6 -> 0.08 | C134: =B7 -> 20 | D134: 0 | E134: =Inputs!$C$165 -> 0.079093281 | F134: =$B$14*$B$13/1000+D134*$B$14*Inputs!$D$147/1000 -> 14.169225 | G134: =(1+B134)^(-$B$8)*(1-(1+B134)^(-C134))/(1-1/(1+B134)) -> 9.0908772 | H134: =($B$9/$B$8)*(1-(1+B134)^(-$B$8))/(1-1/(1+B134)) -> 192.59259 | I134: =(F134*(1-$B$5)-E134*$B$9)*G134-H134 -> -306.92894
A135: Ticket revenue only, life 30 years, replacement at HK share | B135: =B6 -> 0.08 | C135: 30 | D135: 0 | E135: =Inputs!$C$165 -> 0.079093281 | F135: =$B$14*$B$13/1000+D135*$B$14*Inputs!$D$147/1000 -> 14.169225 | G135: =(1+B135)^(-$B$8)*(1-(1+B135)^(-C135))/(1-1/(1+B135)) -> 10.423873 | H135: =($B$9/$B$8)*(1-(1+B135)^(-$B$8))/(1-1/(1+B135)) -> 192.59259 | I135: =(F135*(1-$B$5)-E135*$B$9)*G135-H135 -> -323.69409
A140: Two-way sensitivity: NPV before tax (THB bn), capital cost by cash operating cost share
A141: Capital cost (THB bn) / cost share | B141: 0.7 | C141: =B5 -> 0.77122153 | D141: =Inputs!$C$150 -> 0.9383
A142: 150 | B142: =$B$15*(1-B$141)*$B$27-$A142*($B$28/$B$9)-$B$16*$A142*$B$27 -> -80.791281 | C142: =$B$15*(1-C$141)*$B$27-$A142*($B$28/$B$9)-$B$16*$A142*$B$27 -> -95.902867 | D142: =$B$15*(1-D$141)*$B$27-$A142*($B$28/$B$9)-$B$16*$A142*$B$27 -> -131.35311
A143: 200 | B143: =$B$15*(1-B$141)*$B$27-$A143*($B$28/$B$9)-$B$16*$A143*$B$27 -> -128.93943 | C143: =$B$15*(1-C$141)*$B$27-$A143*($B$28/$B$9)-$B$16*$A143*$B$27 -> -144.05102 | D143: =$B$15*(1-D$141)*$B$27-$A143*($B$28/$B$9)-$B$16*$A143*$B$27 -> -179.50126
A144: 250 | B144: =$B$15*(1-B$141)*$B$27-$A144*($B$28/$B$9)-$B$16*$A144*$B$27 -> -177.08758 | C144: =$B$15*(1-C$141)*$B$27-$A144*($B$28/$B$9)-$B$16*$A144*$B$27 -> -192.19916 | D144: =$B$15*(1-D$141)*$B$27-$A144*($B$28/$B$9)-$B$16*$A144*$B$27 -> -227.64941
A148: Attendance benchmarks (million visits a year)
A149: Park | B149: Attendance (million) | C149: Year | D149: Source
A150: Magic Kingdom (Walt Disney World) | B150: 17.8 | C150: 2024 | D150: TEA/AECOM ranking, reported by Disney Food Blog, 23 October 2025: https://disneyfoodblog.com/2025/10/23/magic-kingdom-is-the-1-most-visited-theme-park-in-the-world-but-the-rest-of-the-list-may-surprise-you
A151: Disneyland Park (California) | B151: 17.3 | C151: 2024 | D151: TEA/AECOM ranking, summarised by BGT Safari, 11 November 2025: https://bgtsafari.com/2025/11/11/the-tea-rankings-are-out-of-for-the-top-25-theme-parks-worldwide-and-almost-half-are-in-asia/
A152: Hong Kong Disneyland | B152: =Inputs!$C$82 -> 7.5 | C152: FY2025 | D152: Hong Kong Disneyland press release, 28 April 2026: https://news.hongkongdisneyland.com/en/press/2026-04-28/
A153: Shanghai Disneyland (approximate) | B153: 14 | C153: 2023 | D153: TEA/AECOM 2023 theme index (approximate)
A154: Tokyo Disney Resort (two parks) | B154: No verified figure | D154: No external source located
A156: Primary break-even attendance (million visits a year) | B156: =B25 -> 43.14715
A157: Multiple of Magic Kingdom attendance | B157: =B25/B150 -> 2.4239972

Sheet Charts
A1: Estimated discounted payback year at WACC (from start of construction)
