Workbook

Sheet Inputs
A1: Parameter | B1: Unit | C1: Value (base case) | D1: Low case | E1: High case | F1: Source
A2: Capex complex thb bn | B2: THB bn | C2: 300 | F2: Thai complex proposal, news reports (12 February 2026)
A3: Capex park high thb bn | B3: THB bn | C3: 200 | F3: Thai park proposal, news reports (12 and 15 May 2026)
A4: Capex park low thb bn | B4: THB bn | C4: 100 | F4: Thai park proposal, news report (27 March 2026)
A5: Claim additional visitors million per year | B5: million visits per year | C5: 10 | F5: Thai government proposal claims, news reports (2026)
A6: Claim revenue thb bn | B6: THB bn | C6: 150 | F6: Thai government proposal claims, news reports (2026)
A7: Claim share of gdp percent per year | B7: percent per year of GDP growth | C7: 1 | F7: Thai government proposal claims, news reports (2026)
A8: Discount rate eirr standard | B8: rate | C8: 0.09 | F8: ADB (2017) Guidelines for the Economic Analysis of Projects, paragraph 194 (printed page 53); DOI. http://dx.doi.org/10.22617/TIM178607-2
A9: Discount rate eirr social sector | B9: rate | C9: 0.06 | F9: ADB (2017) Guidelines for the Economic Analysis of Projects, paragraph 194 (printed page 53); DOI. http://dx.doi.org/10.22617/TIM178607-2
A10: Discount rate social nesdc | B10: rate | C10: 0.07 | F10: NESDC (2024) Guide to Public Investment Project Appraisal, section 6.2.2 (PDF page 28); range in section 6.2.1 (PDF page 26); URL. https://www.nesdc.go.th/wp-content/uploads/2025/05/article_20241009124821.pdf
A11: Discount rate social nesdc pre2025 | B11: rate | C11: 0.12 | F11: NESDC (2024) Guide to Public Investment Project Appraisal, section 6.2.2 (PDF page 28); URL. https://www.nesdc.go.th/wp-content/uploads/2025/05/article_20241009124821.pdf
A12: Conversion factor standard | B12: ratio | C12: 0.7 | F12: NESDC (2024) Guide to Public Investment Project Appraisal, summary of changes (PDF page 5); used when shadow prices cannot be computed; URL. https://www.nesdc.go.th/wp-content/uploads/2025/05/article_20241009124821.pdf
A13: Project life years | B13: years | C13: 20 | F13: NESDC Requirement
... A48: Chonburi foreign arrivals 2019 | B48: persons | C48: 9966574 | F48: https://intelligencecenter.tat.or.th/articles/9907
A49: Utapao expansion progress overall percent | B49: percent complete | F49: https://www.eeco.or.th/en/u-tapao-airport-and-eastern-aviation-city/
A50: Utapao expansion opening year | B50: calendar year | C50: 2031 | F50: https://www.britishaviationgroup.co.uk/?p=24880
A51: High speed rail full service year eeco | B51: calendar year | C51: 2031 | F51: High-speed rail linking three airports, EEC Office. https://www.eeco.or.th/en/high-speed-rail-linking-three-airports/
A52: High speed rail full service year wikipedia | B52: calendar year | C52: 2029 | F52: Don Mueang-Suvarnabhumi-U-Tapao high-speed railway, Wikipedia. https://en.wikipedia.org/wiki/Don_Mueang%E2%80%93Suvarnabhumi%E2%80%93U-Tapao_high-speed_railway
A53: High speed rail status sep 2026 | B53: text | F53: Uttapao and High-Speed Rail: EEC's Make-or-Break Infrastructure Bet, Nation Thailand (7 Sep 2026). https://www.nationthailand.com/business/economy/40070765
A54: Motorway7 utapao extension length km | B54: kilometres | C54: 1.92 | F54: ADB news release, Thailand EEC infrastructure, 6 June 2025. https://www.adb.org/news/adb-supports-resilient-infrastructure-development-eastern-thailand
A55: Motorway7 utapao extension completion year | B55: calendar year | C55: 2028 | F55: https://www.thansettakij.com/economy/megaproject/630463
A56: Pattaya map ta phut motorway7 opening year | B56: calendar year (opened August 2020) | C56: 2020 | F56: Thai Prime Minister opens Pattaya-Map Ta Phut Highway, Pattaya Mail (24 Aug 2020). https://www.pattayamail.com/news/thai-prime-minister-opens-pattaya-map-ta-phut-highway-312223
A57: Tat spend per trip all nationalities 2023 | B57: THB per trip | C57: 50900 | F57: No external source located
A58: Tat spend per trip middle eastern 2023 | B58: THB per person per trip | C58: 88512 | F58: No external source located
A59: Tat spend per day uae 2023 | B59: THB per person per day | C59: 8834 | F59: No external source located
A60: Tat spend per night by nationality 2024 2025 | B60: THB per person per night | F60: No external source located
A61: Tat spend per trip by nationality 2024 2025 official | B61: THB per person per trip | F61: https://www.tatnews.org/?p=84576
A62: Mots spend per trip all tourists 2019 | B62: THB per international tourist per trip | C62: 48580 | F62: https://www.mots.go.th/download/article/article_20200123132729.pdf
A63: Mots spend per day all tourists 2019 | B63: THB per international tourist per day | C63: 5172.29 | F63: https://www.mots.go.th/download/article/article_20201104090605.pdf
A64: Intl avg length of stay 2016 days | B64: days | C64: 9.6 | F64: https://www.nso.go.th/public/e-book/Indicators-Economic/Indicators-Economic-2562/files/assets/basic-html/page134.html
A65: Intl avg length of stay 2024 days | B65: days | C65: 9.4 | F65: https://www.mots.go.th/images/v2022_c1331820-8936-4423-84cd-65278cebf658.xlsx
A66: Intl first visit share 2024 | B66: percent of international arrivals on first visit | F66: No external source located
A67: Thai domestic spend per trip 2024 | B67: THB per person per domestic trip | C67: 4000 | F67: No external source located
A68: Thai resident attraction visit share 2024 | B68: percent of attraction visits by Thai residents | F68: No external source located
A69: Intl arrivals 2025 | B69: persons | C69: 32974321 | F69: https://www.mots.go.th/images/v2022_5a7fbad7-1fcf-4410-a387-f29bb17486e2.xlsx
A70: Intl arrivals 2024 | B70: persons | C70: 35545714 | F70: https://www.mots.go.th/images/v2022_875a5789-3bcc-4700-bf55-b86fa7f1053c.xlsx
A71: Intl arrivals 2019 | B71: persons | C71: 39916251 | F71: https://www.mots.go.th/download/article/article_20201103140333.xlsx
A72: Intl arrivals 2020 | B72: persons | C72: 6725000 | F72: https://www.nso.go.th/public/e-book/Indicators-Economic/Thai_Economic_Indicators_2025/158
A73: Intl tourism receipts 2025 mots | B73: THB bn | C73: 1587.208 | F73: https://www.mots.go.th/images/v2022_5a7fbad7-1fcf-4410-a387-f29bb17486e2.xlsx
A74: Intl tourism receipts 2024 mots | B74: THB bn | C74: 1612.603 | F74: https://www.mots.go.th/images/v2022_c1331820-8936-4423-84cd-65278cebf658.xlsx
A75: Intl tourism receipts usd wdi 2019 | B75: US$ bn | C75: 59.81 | F75: World Bank API, indicator ST.INT.TVLR.CD (international tourism receipts for travel items), Thailand. https://api.worldbank.org/v2/country/THA/indicator/ST.INT.TVLR.CD?format=json&date=2015:2025&per_page=100
A76: Intl tourism receipts usd wdi 2020 | B76: US$ bn | C76: 14.198 | F76: World Bank API, indicator ST.INT.TVLR.CD (international tourism receipts for travel items), Thailand. https://api.worldbank.org/v2/country/THA/indicator/ST.INT.TVLR.CD?format=json&date=2015:2025&per_page=100
A77: Intl tourism receipts bot thb bn 2019 2025 | B77: THB bn | C77: 1400 | F77: No external source located
A78: Ticket price ocean park adult hkd | B78: HK$ per adult admission | C78: 498 | F78: Australasian Leisure Management, Ocean Park entrance prices (2019), https://www.ausleisure.com.au/news/entrance-prices-at-hong-kongs-ocean-park-rise-by-4
A79: Ticket price universal studios singapore adult sgd | B79: SGD per adult ticket | C79: 76 | F79: https://www.rwsentosa.com/en/play/universal-studios-singapore/tickets
A80: Tsa attraction recreation spending share 2022 | B80: percent of visitor spending on attractions or recreation | F80: No external source located
A81: Hk disneyland attendance fy2019 | B81: million visitors | C81: 6.5 | F81: https://hkcorporate.hongkongdisneyland.com/pdf/AnnualBusinessReview19.pdf
A82: Hk disneyland attendance fy2024 | B82: million visitors | C82: 7.7 | F82: https://hkcorporate.hongkongdisneyland.com/pdf/AnnualBusinessReview24.pdf
A83: Hk disneyland attendance fy2025 | B83: million visitors | C83: 7.5 | F83: https://news.hongkongdisneyland.com/en/press/2026-04-28/
A84: Hk disneyland revenue fy2025 hkd m | B84: HK$ million | C84: 8694 | F84: https://hkcorporate.hongkongdisneyland.com/pdf/AnnualBusinessReview25.pdf
A85: Hk disneyland net profit fy2025 hkd m | B85: HK$ million | C85: 536 | F85: https://hkcorporate.hongkongdisneyland.com/pdf/AnnualBusinessReview25.pdf
A86: Hk disneyland adult ticket tier1 hkd | B86: HK$ per adult ticket | C86: 669 | F86: https://www.hongkongdisneyland.com/offers-discounts/travel-industry-salute/
A87: Hk disneyland adult ticket tier4 peak hkd | B87: HK$ per adult ticket | C87: 939 | F87: https://www.hongkongdisneyland.com/offers-discounts/travel-industry-salute/
A88: Hk disneyland visitor share local fy2019 | B88: percent of attendance | C88: 41 | F88: https://hkcorporate.hongkongdisneyland.com/pdf/AnnualBusinessReview19.pdf
A89: Hk disneyland visitor share mainland fy2019 | B89: percent of attendance | C89: 33 | F89: https://hkcorporate.hongkongdisneyland.com/pdf/AnnualBusinessReview19.pdf
A90: Hk disneyland visitor share other fy2019 | B90: percent of attendance | C90: 26 | F90: https://hkcorporate.hongkongdisneyland.com/pdf/AnnualBusinessReview19.pdf
A91: Ocean park attendance fy2024 25 | B91: million visitors | C91: 3.46 | F91: https://corporate.oceanpark.com.hk/en/media-partnerships/press-release/
A92: Ocean park non local visitors fy2024 25 | B92: million visitors | C92: 1.25 | F92: https://corporate.oceanpark.com.hk/en/media-partnerships/press-release/
... A99: Ocean park adult admission 2019 hkd | B99: HK$ per adult ticket | C99: 498 | F99: No external source located
A100: Universal studios singapore attendance 2024 million | B100: million visitors | F100: No external source located
A101: Lotte world adult ticket 2026 krw | B101: KRW per adult ticket (full-day pass) | C101: 67000 | F101: SBS Biz, Lotte World to raise adult ticket price, article dated 17 March 2026, lead paragraph. https://biz.sbs.co.kr/amp/article/20000297877
A102: Lotte world visitors 2023 million | B102: million persons | C102: 5.193 | F102: https://know.tour.go.kr/ptourknow/tourgoInfoView19Re.do?seq=103270
A103: Lotte world visitors 2024 million | B103: million persons | C103: 5.257 | F103: https://know.tour.go.kr/stat/visitStatDis/rankingStat.do
A104: Shanghai disneyland attendance 2024 million | B104: million visitors | C104: 14.7 | F104: Shanghai Municipal Government news, Shanghai Disneyland secures global top 5 position with record attendance, 27 October 2025, body paragraph on attendance. https://english.shanghai.gov.cn/en-Latest-WhatsNew/20251027/63097f5dd6ff4d2dad7e736573ead8d6.html
A105: Shanghai disneyland attendance 2019 million | B105: million visitors | C105: 11.21 | F105: TEA and AECOM Theme Index 2019, Top 25 table, rank 10, https://blooloop.com/files/75972/tea-report-2019.pdf
A106: Thailand 10y government bond yield 2026 10 14 | B106: rate per year | C106: 0.0232 | F106: No external source located
A107: Corporate income tax rate standard | B107: rate of net profit | C107: 0.2 | F107: Revenue Department, corporate income tax, https://www.rd.go.th/english/6044.html
A108: Vat statutory rate | B108: rate | C108: 0.1 | F108: https://www.rd.go.th/english/37732.html
A109: Vat reduced rate 2026 2027 | B109: rate, including local tax | C109: 0.07 | F109: KPMG TaxNewsFlash, same article, first paragraph on Royal Decree No. 807. Temporary reduced rate for 1 October 2026 to 30 September 2027. It must be checked again after 30 September 2027.
A110: Adb economic horizon years low | B110: years | C110: 20 | F110: ADB (2017) Guidelines for the Economic Analysis of Projects, printed pages 47 to 48, paragraph 176. https://www.adb.org/sites/default/files/institutional-document/32256/economic-analysis-projects.pdf
A111: Adb economic horizon years high | B111: years | C111: 30 | F111: ADB (2017) Guidelines for the Economic Analysis of Projects, printed pages 47 to 48, paragraph 176. https://www.adb.org/sites/default/files/institutional-document/32256/economic-analysis-projects.pdf
A112: Adb dam railway operating years low | B112: years | C112: 20 | F112: ADB (2017), printed page 64, Appendix 3, paragraph 2. https://www.adb.org/sites/default/files/institutional-document/32256/economic-analysis-projects.pdf
... A140: Cbre pattaya occupancy h2 2025 | B140: share | C140: 0.655 | F140: CBRE, Pattaya Overall Figures H2 2025. https://mktgdocs.cbre.com/2299/175bc843-73b5-4940-a859-14bd0f57a6a1-1295998069/Pattaya-Overall-Figures-H2-202.pdf
A141: Project life years | B141: years | C141: 20 | D141: 20 | E141: 25 | F141: NESDC Requirement
A142: Construction years | B142: years | C142: 2 | D142: 3 | E142: 2 | F142: ADB (2017) Guidelines, Appendix 3 illustrative implementation period, https://www.adb.org/sites/default/files/institutional-document/32256/economic-analysis-projects.pdf
A143: Wacc financial | B143: rate | C143: 0.08 | D143: 0.1 | E143: 0.07 | F143: NESDC Requirement
A144: Attendance million per year | B144: million visits per year | C144: 7.5 | D144: 3.46 | E144: 14.7 | F144: NESDC Assumption
A145: International share | B145: share of attendance | C145: 0.59 | D145: 0.36 | E145: 0.75 | F145: Hong Kong Disneyland Annual Business Review FY2019, origin of visitors, https://hkcorporate.hongkongdisneyland.com/pdf/AnnualBusinessReview19.pdf
A146: Incremental share | B146: share | C146: 0.3 | D146: 0.1 | E146: 0.5 | F146: NESDC Assumption
A147: Displacement share | B147: share | C147: 0.3 | D147: 0.5 | E147: 0.1 | F147: NESDC Assumption
A148: Spend per visit thb | B148: THB per incremental visit | C148: 10000 | D148: 1862 | E148: 20000 | F148: NESDC Assumption (base and high); Oriental Land Co., Tokyo Disney Resort FY3/2026, on-site spending per guest (low)
A149: Domestic retention share | B149: share | C149: 0.5 | D149: 0.3 | E149: 0.7 | F149: NESDC Assumption
A150: Tax share of spend | B150: share of net spending | C150: 0.065421 | D150: 0 | E150: 0.090909 | F150: NESDC Assumption; VAT rate, Revenue Department, https://www.rd.go.th/english/37732.html
A151: Opex share | B151: ratio of revenue | C151: 0.9383 | D151: 1.2146 | E151: 0.7 | F151: Hong Kong Disneyland Annual Business Review FY2025, https://hkcorporate.hongkongdisneyland.com/pdf/AnnualBusinessReview25.pdf
A152: Ticket revenue per visit thb | B152: THB per visit | C152: 2877 | D152: 2158 | E152: 4038 | F152: Hong Kong Disneyland adult ticket tier 1, https://www.hongkongdisneyland.com/offers-discounts/travel-industry-salute/
... A161: Occupancy ceiling serving site | B161: share | C161: 0.85 | D161: 0.8042 | E161: 0.9 | F161: NESDC Assumption
A163: Park-only operator inputs
A164: Park-only capital cost | B164: THB bn | C164: =C3 -> 200 | F164: Nation Thailand, 12 February 2026, https://www.nationthailand.com/blogs/business/investment/40062428
A165: Replacement capex, share of capital per operating year | B165: share | C165: 0 | F165: NESDC Assumption
A166: Hong Kong depreciation share of noncurrent assets | B166: share per year | C166: =C134/C135 -> 0.079093281 | F166: Hong Kong Disneyland Annual Business Review FY2025, https://hkcorporate.hongkongdisneyland.com/pdf/AnnualBusinessReview25.pdf
A167: Corporate income tax rate | B167: ratio | C167: =C107 -> 0.2 | F167: Revenue Department, corporate income tax, https://www.rd.go.th/english/6044.html
A168: Tax depreciation years | B168: years | C168: =C127 -> 20 | F168: NESDC Assumption

Sheet Appraisal
A1: Park-only operator financial appraisal (THB billion unless stated)
A4: Parameter | B4: Park-only | C4: Complex, 300 bn
A5: Cash operating cost, share of revenue | B5: =Inputs!$C$133/Inputs!$C$84 -> 0.77122153 | C5: =B5 -> 0.77122153
A6: WACC | B6: =Inputs!$C$143 -> 0.08 | C6: =B6 -> 0.08
A7: Operating life (years) | B7: =Inputs!$C$141 -> 20 | C7: =B7 -> 20
A8: Construction years | B8: =Inputs!$C$142 -> 2 | C8: =B8 -> 2
A9: Capital cost (THB bn) | B9: =Inputs!$C$164 -> 200 | C9: =Inputs!$C$2 -> 300
A10: Attendance (million visits a year) | B10: =Inputs!$C$144 -> 7.5 | C10: =B10 -> 7.5
A11: International share of attendance | B11: =Inputs!$C$145 -> 0.59 | C11: =B11 -> 0.59
A12: Physical visit cap (million visits a year) | B12: =MIN(Inputs!$C$26/Inputs!$C$155,Inputs!$C$159*365*Inputs!$C$154/Inputs!$C$153)/1000000 -> 1.85 | C12: =B12 -> 1.85
A13: Ticket revenue per visit (THB) | B13: =Inputs!$C$152 -> 2877 | C13: =B13 -> 2877
A14: Operator visits per operating year (million) | B14: =B10-MAX(B10*B11-B12,0) -> 4.925 | C14: =B14 -> 4.925
A15: Operator revenue per operating year (THB bn) | B15: =B14*(B13+B19*Inputs!$D$148)/1000 -> 23.339575 | C15: =B14*(C13+C19*Inputs!$D$148)/1000 -> 14.169225
A16: Replacement capex, share of capital per operating year | B16: =Inputs!$C$165 -> 0 | C16: =B16 -> 0
A17: Corporate income tax rate | B17: =Inputs!$C$167 -> 0.2 | C17: =B17 -> 0.2
A18: Tax depreciation years | B18: =Inputs!$C$168 -> 20 | C18: =B18 -> 20
A19: On-site income included (1 = yes) | B19: 1 | C19: 0
A20: Results | B20: Park-only | C20: Complex, 300 bn
A21: Operator NPV before tax at WACC (THB bn) | B21: =SUM(K41:K63) -> -144.05102 | C21: =(C15*(1-C5)-C16*C9)*B27-(C9/B9)*B28 -> -259.41978
A22: Operator NPV after tax (THB bn) | B22: =IF($B$18<$B$7,"n/a",SUM(R41:R63)) -> -144.05102 | C22: =IF(C18<C7,"n/a",C21) -> -259.41978
A23: Operator IRR after tax | B23: =IF($B$18<$B$7,"n/a",IRR(Q41:Q63,-0.1)) -> -0.05150944 | C23: n/a
A24: Break-even capital cost (THB bn) | B24: =B15*(1-B5)*B27/(B16*B27+B28/B9) -> 50.408561 | C24: =B24 -> 50.408561
A25: Break-even attendance (million visits a year) | B25: =B10-B21/((1-B5)*(B13+B19*Inputs!$D$148)/1000*(1-B11)*B27) -> 43.14715 | C25: =B10-C21/((1-C5)*C13/1000*(1-C11)*B27) -> 113.24465
A27: Annuity factor over operating years | B27: =SUMPRODUCT(B41:B63,D41:D63) -> 9.0908772
A28: Present value of capital cost (THB bn) | B28: =SUMPRODUCT(E41:E63,B41:B63) -> 192.59259
A32: Tax depreciation covers the operating life | B32: =IF(B18<B7,"No","Yes") -> Yes | C32: =IF(C18<C7,"No","Yes") -> Yes
A33: Cumulative cash flow over the operating life, before tax (THB bn) | B33: =SUM(J41:J63) -> -93.208156 | C33: =(C15*(1-C5)-C16*C9)*B7-C9 -> -235.16773
A34: Years of operation needed for nominal payback | B34: =IF(B15*(1-B5)-B16*B9<=0,"never",B9/(B15*(1-B5)-B16*B9)) -> 37.456044 | C34: =IF(C15*(1-C5)-C16*C9<=0,"never",C9/(C15*(1-C5)-C16*C9)) -> 92.546503
A35: Estimated nominal payback year (from start of construction) | B35: =IF(ISNUMBER(B34),B8+B34,"never") -> 39.456044 | C35: =IF(ISNUMBER(C34),C8+C34,"never") -> 94.546503
A36: Nominal payback within the operating life | B36: =IF(ISNUMBER(B34),IF(B34<=B7,"Yes","No"),"No") -> No | C36: =IF(ISNUMBER(C34),IF(C34<=C7,"Yes","No"),"No") -> No
A37: Estimated discounted payback year at WACC (from start of construction) | B37: =IF(B15*(1-B5)-B16*B9<=0,"never",IF(B28*B6*(1+B6)^(B8-1)/(B15*(1-B5)-B16*B9)>=1,"never",B8-LN(1-B28*B6*(1+B6)^(B8-1)/(B15*(1-B5)-B16*B9))/LN(1+B6))) -> never | C37: =IF(C15*(1-C5)-C16*C9<=0,"never",IF((C9/B9)*B28*C6*(1+C6)^(C8-1)/(C15*(1-C5)-C16*C9)>=1,"never",C8-LN(1-(C9/B9)*B28*C6*(1+C6)^(C8-1)/(C15*(1-C5)-C16*C9))/LN(1+C6))) -> never
A39: Annual ledger, park-only
A40: Year | B40: Discount factor | C40: Construction | D40: Operating | E40: Capital cost | F40: Operator visits (million) | G40: Revenue | H40: Cash operating cost | I40: Replacement capex | J40: Cash flow before tax | K40: Present value before tax | L40: Tax depreciation | M40: Taxable income | N40: Cumulative taxable income | O40: Cumulative tax due | P40: Tax paid | Q40: Cash flow after tax | R40: Present value after tax | S40: Cumulative cash flow after tax | U40: Capital outflow, absolute (THB bn) | V40: Operating cash flow (THB bn)
A41: 0 | B41: =1/(1+$B$6)^A41 -> 1 | C41: =IF(A41<$B$8,1,0) -> 1 | D41: =IF(AND(A41>=$B$8,A41<$B$8+$B$7),1,0) -> 0 | E41: =C41*$B$9/$B$8 -> 100 | F41: =D41*$B$14 -> 0 | G41: =F41*($B$13+$B$19*Inputs!$D$148)/1000 -> 0 | H41: =$B$5*G41 -> 0 | I41: =D41*$B$16*$B$9 -> 0 | J41: =G41-H41-E41-I41 -> -100 | K41: =J41*B41 -> -100 | L41: =IF(AND(A41>=$B$8,A41<$B$8+$B$18),$B$9/$B$18,0) -> 0 | M41: =G41-H41-L41 -> 0 | N41: =SUM($M$41:M41) -> 0 | O41: =$B$17*MAX(0,N41) -> 0 | P41: =MAX(0,O41) -> 0 | Q41: =J41-P41 -> -100 | R41: =Q41*B41 -> -100 | S41: =SUM($Q$41:Q41) -> -100 | U41: =IF(J41<0,-J41,NA()) -> 100 | V41: =IF(J41>0,J41,NA()) -> #N/A
A42: 1 | B42: =1/(1+$B$6)^A42 -> 0.92592593 | C42: =IF(A42<$B$8,1,0) -> 1 | D42: =IF(AND(A42>=$B$8,A42<$B$8+$B$7),1,0) -> 0 | E42: =C42*$B$9/$B$8 -> 100 | F42: =D42*$B$14 -> 0 | G42: =F42*($B$13+$B$19*Inputs!$D$148)/1000 -> 0 | H42: =$B$5*G42 -> 0 | I42: =D42*$B$16*$B$9 -> 0 | J42: =G42-H42-E42-I42 -> -100 | K42: =J42*B42 -> -92.592593 | L42: =IF(AND(A42>=$B$8,A42<$B$8+$B$18),$B$9/$B$18,0) -> 0 | M42: =G42-H42-L42 -> 0 | N42: =SUM($M$41:M42) -> 0 | O42: =$B$17*MAX(0,N42) -> 0 | P42: =MAX(0,O42-O41) -> 0 | Q42: =J42-P42 -> -100 | R42: =Q42*B42 -> -92.592593 | S42: =SUM($Q$41:Q42) -> -200 | U42: =IF(J42<0,-J42,NA()) -> 100 | V42: =IF(J42>0,J42,NA()) -> #N/A
A43: 2 | B43: =1/(1+$B$6)^A43 -> 0.85733882 | C43: =IF(A43<$B$8,1,0) -> 0 | D43: =IF(AND(A43>=$B$8,A43<$B$8+$B$7),1,0) -> 1 | E43: =C43*$B$9/$B$8 -> 0 | F43: =D43*$B$14 -> 4.925 | G43: =F43*($B$13+$B$19*Inputs!$D$148)/1000 -> 23.339575 | H43: =$B$5*G43 -> 17.999983 | I43: =D43*$B$16*$B$9 -> 0 | J43: =G43-H43-E43-I43 -> 5.3395922 | K43: =J43*B43 -> 4.5778397 | L43: =IF(AND(A43>=$B$8,A43<$B$8+$B$18),$B$9/$B$18,0) -> 10 | M43: =G43-H43-L43 -> -4.6604078 | N43: =SUM($M$41:M43) -> -4.6604078 | O43: =$B$17*MAX(0,N43) -> 0 | P43: =MAX(0,O43-O42) -> 0 | Q43: =J43-P43 -> 5.3395922 | R43: =Q43*B43 -> 4.5778397 | S43: =SUM($Q$41:Q43) -> -194.66041 | U43: =IF(J43<0,-J43,NA()) -> #N/A | V43: =IF(J43>0,J43,NA()) -> 5.3395922
A44: 3 | B44: =1/(1+$B$6)^A44 -> 0.79383224 | C44: =IF(A44<$B$8,1,0) -> 0 | D44: =IF(AND(A44>=$B$8,A44<$B$8+$B$7),1,0) -> 1 | E44: =C44*$B$9/$B$8 -> 0 | F44: =D44*$B$14 -> 4.925 | G44: =F44*($B$13+$B$19*Inputs!$D$148)/1000 -> 23.339575 | H44: =$B$5*G44 -> 17.999983 | I44: =D44*$B$16*$B$9 -> 0 | J44: =G44-H44-E44-I44 -> 5.3395922 | K44: =J44*B44 -> 4.2387405 | L44: =IF(AND(A44>=$B$8,A44<$B$8+$B$18),$B$9/$B$18,0) -> 10 | M44: =G44-H44-L44 -> -4.6604078 | N44: =SUM($M$41:M44) -> -9.3208156 | O44: =$B$17*MAX(0,N44) -> 0 | P44: =MAX(0,O44-O43) -> 0 | Q44: =J44-P44 -> 5.3395922 | R44: =Q44*B44 -> 4.2387405 | S44: =SUM($Q$41:Q44) -> -189.32082 | U44: =IF(J44<0,-J44,NA()) -> #N/A | V44: =IF(J44>0,J44,NA()) -> 5.3395922
A45: 4 | B45: =1/(1+$B$6)^A45 -> 0.73502985 | C45: =IF(A45<$B$8,1,0) -> 0 | D45: =IF(AND(A45>=$B$8,A45<$B$8+$B$7),1,0) -> 1 | E45: =C45*$B$9/$B$8 -> 0 | F45: =D45*$B$14 -> 4.925 | G45: =F45*($B$13+$B$19*Inputs!$D$148)/1000 -> 23.339575 | H45: =$B$5*G45 -> 17.999983 | I45: =D45*$B$16*$B$9 -> 0 | J45: =G45-H45-E45-I45 -> 5.3395922 | K45: =J45*B45 -> 3.9247597 | L45: =IF(AND(A45>=$B$8,A45<$B$8+$B$18),$B$9/$B$18,0) -> 10 | M45: =G45-H45-L45 -> -4.6604078 | N45: =SUM($M$41:M45) -> -13.981223 | O45: =$B$17*MAX(0,N45) -> 0 | P45: =MAX(0,O45-O44) -> 0 | Q45: =J45-P45 -> 5.3395922 | R45: =Q45*B45 -> 3.9247597 | S45: =SUM($Q$41:Q45) -> -183.98122 | U45: =IF(J45<0,-J45,NA()) -> #N/A | V45: =IF(J45>0,J45,NA()) -> 5.3395922
A46: 5 | B46: =1/(1+$B$6)^A46 -> 0.6805832 | C46: =IF(A46<$B$8,1,0) -> 0 | D46: =IF(AND(A46>=$B$8,A46<$B$8+$B$7),1,0) -> 1 | E46: =C46*$B$9/$B$8 -> 0 | F46: =D46*$B$14 -> 4.925 | G46: =F46*($B$13+$B$19*Inputs!$D$148)/1000 -> 23.339575 | H46: =$B$5*G46 -> 17.999983 | I46: =D46*$B$16*$B$9 -> 0 | J46: =G46-H46-E46-I46 -> 5.3395922 | K46: =J46*B46 -> 3.6340367 | L46: =IF(AND(A46>=$B$8,A46<$B$8+$B$18),$B$9/$B$18,0) -> 10 | M46: =G46-H46-L46 -> -4.6604078 | N46: =SUM($M$41:M46) -> -18.641631 | O46: =$B$17*MAX(0,N46) -> 0 | P46: =MAX(0,O46-O45) -> 0 | Q46: =J46-P46 -> 5.3395922 | R46: =Q46*B46 -> 3.6340367 | S46: =SUM($Q$41:Q46) -> -178.64163 | U46: =IF(J46<0,-J46,NA()) -> #N/A | V46: =IF(J46>0,J46,NA()) -> 5.3395922
A47: 6 | B47: =1/(1+$B$6)^A47 -> 0.63016963 | C47: =IF(A47<$B$8,1,0) -> 0 | D47: =IF(AND(A47>=$B$8,A47<$B$8+$B$7),1,0) -> 1 | E47: =C47*$B$9/$B$8 -> 0 | F47: =D47*$B$14 -> 4.925 | G47: =F47*($B$13+$B$19*Inputs!$D$148)/1000 -> 23.339575 | H47: =$B$5*G47 -> 17.999983 | I47: =D47*$B$16*$B$9 -> 0 | J47: =G47-H47-E47-I47 -> 5.3395922 | K47: =J47*B47 -> 3.3648488 | L47: =IF(AND(A47>=$B$8,A47<$B$8+$B$18),$B$9/$B$18,0) -> 10 | M47: =G47-H47-L47 -> -4.6604078 | N47: =SUM($M$41:M47) -> -23.302039 | O47: =$B$17*MAX(0,N47) -> 0 | P47: =MAX(0,O47-O46) -> 0 | Q47: =J47-P47 -> 5.3395922 | R47: =Q47*B47 -> 3.3648488 | S47: =SUM($Q$41:Q47) -> -173.30204 | U47: =IF(J47<0,-J47,NA()) -> #N/A | V47: =IF(J47>0,J47,NA()) -> 5.3395922
A48: 7 | B48: =1/(1+$B$6)^A48 -> 0.5834904 | C48: =IF(A48<$B$8,1,0) -> 0 | D48: =IF(AND(A48>=$B$8,A48<$B$8+$B$7),1,0) -> 1 | E48: =C48*$B$9/$B$8 -> 0 | F48: =D48*$B$14 -> 4.925 | G48: =F48*($B$13+$B$19*Inputs!$D$148)/1000 -> 23.339575 | H48: =$B$5*G48 -> 17.999983 | I48: =D48*$B$16*$B$9 -> 0 | J48: =G48-H48-E48-I48 -> 5.3395922 | K48: =J48*B48 -> 3.1156008 | L48: =IF(AND(A48>=$B$8,A48<$B$8+$B$18),$B$9/$B$18,0) -> 10 | M48: =G48-H48-L48 -> -4.6604078 | N48: =SUM($M$41:M48) -> -27.962447 | O48: =$B$17*MAX(0,N48) -> 0 | P48: =MAX(0,O48-O47) -> 0 | Q48: =J48-P48 -> 5.3395922 | R48: =Q48*B48 -> 3.1156008 | S48: =SUM($Q$41:Q48) -> -167.96245 | U48: =IF(J48<0,-J48,NA()) -> #N/A | V48: =IF(J48>0,J48,NA()) -> 5.3395922
A49: 8 | B49: =1/(1+$B$6)^A49 -> 0.54026888 | C49: =IF(A49<$B$8,1,0) -> 0 | D49: =IF(AND(A49>=$B$8,A49<$B$8+$B$7),1,0) -> 1 | E49: =C49*$B$9/$B$8 -> 0 | F49: =D49*$B$14 -> 4.925 | G49: =F49*($B$13+$B$19*Inputs!$D$148)/1000 -> 23.339575 | H49: =$B$5*G49 -> 17.999983 | I49: =D49*$B$16*$B$9 -> 0 | J49: =G49-H49-E49-I49 -> 5.3395922 | K49: =J49*B49 -> 2.8848155 | L49: =IF(AND(A49>=$B$8,A49<$B$8+$B$18),$B$9/$B$18,0) -> 10 | M49: =G49-H49-L49 -> -4.6604078 | N49: =SUM($M$41:M49) -> -32.622855 | O49: =$B$17*MAX(0,N49) -> 0 | P49: =MAX(0,O49-O48) -> 0 | Q49: =J49-P49 -> 5.3395922 | R49: =Q49*B49 -> 2.8848155 | S49: =SUM($Q$41:Q49) -> -162.62285 | U49: =IF(J49<0,-J49,NA()) -> #N/A | V49: =IF(J49>0,J49,NA()) -> 5.3395922
A50: 9 | B50: =1/(1+$B$6)^A50 -> 0.50024897 | C50: =IF(A50<$B$8,1,0) -> 0 | D50: =IF(AND(A50>=$B$8,A50<$B$8+$B$7),1,0) -> 1 | E50: =C50*$B$9/$B$8 -> 0 | F50: =D50*$B$14 -> 4.925 | G50: =F50*($B$13+$B$19*Inputs!$D$148)/1000 -> 23.339575 | H50: =$B$5*G50 -> 17.999983 | I50: =D50*$B$16*$B$9 -> 0 | J50: =G50-H50-E50-I50 -> 5.3395922 | K50: =J50*B50 -> 2.6711255 | L50: =IF(AND(A50>=$B$8,A50<$B$8+$B$18),$B$9/$B$18,0) -> 10 | M50: =G50-H50-L50 -> -4.6604078 | N50: =SUM($M$41:M50) -> -37.283262 | O50: =$B$17*MAX(0,N50) -> 0 | P50: =MAX(0,O50-O49) -> 0 | Q50: =J50-P50 -> 5.3395922 | R50: =Q50*B50 -> 2.6711255 | S50: =SUM($Q$41:Q50) -> -157.28326 | U50: =IF(J50<0,-J50,NA()) -> #N/A | V50: =IF(J50>0,J50,NA()) -> 5.3395922
A51: 10 | B51: =1/(1+$B$6)^A51 -> 0.46319349 | C51: =IF(A51<$B$8,1,0) -> 0 | D51: =IF(AND(A51>=$B$8,A51<$B$8+$B$7),1,0) -> 1 | E51: =C51*$B$9/$B$8 -> 0 | F51: =D51*$B$14 -> 4.925 | G51: =F51*($B$13+$B$19*Inputs!$D$148)/1000 -> 23.339575 | H51: =$B$5*G51 -> 17.999983 | I51: =D51*$B$16*$B$9 -> 0 | J51: =G51-H51-E51-I51 -> 5.3395922 | K51: =J51*B51 -> 2.4732643 | L51: =IF(AND(A51>=$B$8,A51<$B$8+$B$18),$B$9/$B$18,0) -> 10 | M51: =G51-H51-L51 -> -4.6604078 | N51: =SUM($M$41:M51) -> -41.94367 | O51: =$B$17*MAX(0,N51) -> 0 | P51: =MAX(0,O51-O50) -> 0 | Q51: =J51-P51 -> 5.3395922 | R51: =Q51*B51 -> 2.4732643 | S51: =SUM($Q$41:Q51) -> -151.94367 | U51: =IF(J51<0,-J51,NA()) -> #N/A | V51: =IF(J51>0,J51,NA()) -> 5.3395922
A52: 11 | B52: =1/(1+$B$6)^A52 -> 0.42888286 | C52: =IF(A52<$B$8,1,0) -> 0 | D52: =IF(AND(A52>=$B$8,A52<$B$8+$B$7),1,0) -> 1 | E52: =C52*$B$9/$B$8 -> 0 | F52: =D52*$B$14 -> 4.925 | G52: =F52*($B$13+$B$19*Inputs!$D$148)/1000 -> 23.339575 | H52: =$B$5*G52 -> 17.999983 | I52: =D52*$B$16*$B$9 -> 0 | J52: =G52-H52-E52-I52 -> 5.3395922 | K52: =J52*B52 -> 2.2900596 | L52: =IF(AND(A52>=$B$8,A52<$B$8+$B$18),$B$9/$B$18,0) -> 10 | M52: =G52-H52-L52 -> -4.6604078 | N52: =SUM($M$41:M52) -> -46.604078 | O52: =$B$17*MAX(0,N52) -> 0 | P52: =MAX(0,O52-O51) -> 0 | Q52: =J52-P52 -> 5.3395922 | R52: =Q52*B52 -> 2.2900596 | S52: =SUM($Q$41:Q52) -> -146.60408 | U52: =IF(J52<0,-J52,NA()) -> #N/A | V52: =IF(J52>0,J52,NA()) -> 5.3395922
A53: 12 | B53: =1/(1+$B$6)^A53 -> 0.39711376 | C53: =IF(A53<$B$8,1,0) -> 0 | D53: =IF(AND(A53>=$B$8,A53<$B$8+$B$7),1,0) -> 1 | E53: =C53*$B$9/$B$8 -> 0 | F53: =D53*$B$14 -> 4.925 | G53: =F53*($B$13+$B$19*Inputs!$D$148)/1000 -> 23.339575 | H53: =$B$5*G53 -> 17.999983 | I53: =D53*$B$16*$B$9 -> 0 | J53: =G53-H53-E53-I53 -> 5.3395922 | K53: =J53*B53 -> 2.1204255 | L53: =IF(AND(A53>=$B$8,A53<$B$8+$B$18),$B$9/$B$18,0) -> 10 | M53: =G53-H53-L53 -> -4.6604078 | N53: =SUM($M$41:M53) -> -51.264486 | O53: =$B$17*MAX(0,N53) -> 0 | P53: =MAX(0,O53-O52) -> 0 | Q53: =J53-P53 -> 5.3395922 | R53: =Q53*B53 -> 2.1204255 | S53: =SUM($Q$41:Q53) -> -141.26449 | U53: =IF(J53<0,-J53,NA()) -> #N/A | V53: =IF(J53>0,J53,NA()) -> 5.3395922
... A63: 22 | B63: =1/(1+$B$6)^A63 -> 0.18394051 | C63: =IF(A63<$B$8,1,0) -> 0 | D63: =IF(AND(A63>=$B$8,A63<$B$8+$B$7),1,0) -> 0 | E63: =C63*$B$9/$B$8 -> 0 | F63: =D63*$B$14 -> 0 | G63: =F63*($B$13+$B$19*Inputs!$D$148)/1000 -> 0 | H63: =$B$5*G63 -> 0 | I63: =D63*$B$16*$B$9 -> 0 | J63: =G63-H63-E63-I63 -> 0 | K63: =J63*B63 -> 0 | L63: =IF(AND(A63>=$B$8,A63<$B$8+$B$18),$B$9/$B$18,0) -> 0 | M63: =G63-H63-L63 -> 0 | N63: =SUM($M$41:M63) -> -93.208156 | O63: =$B$17*MAX(0,N63) -> 0 | P63: =MAX(0,O63-O62) -> 0 | Q63: =J63-P63 -> 0 | R63: =Q63*B63 -> 0 | S63: =SUM($Q$41:Q63) -> -93.208156 | U63: =IF(J63<0,-J63,NA()) -> #N/A | V63: =IF(J63>0,J63,NA()) -> #N/A
A66: Sensitivity cases
A67: Case | B67: Capital cost factor | C67: Opex factor | D67: Revenue factor | E67: Opening delay (years) | F67: Annuity factor | G67: NPV before tax, park-only | H67: NPV before tax, complex (reference) | I67: Replacement share | J67: Taxable income, park-only | K67: NPV after tax, park-only | L67: Taxable income, complex | M67: NPV after tax, complex | N67: Chart label
A68: Base | B68: 1 | C68: 1 | D68: 1 | E68: 0 | F68: =SUMPRODUCT($B$41:$B$63*($A$41:$A$63>=$B$8+E68)*($A$41:$A$63<$B$8+E68+$B$7)) -> 9.0908772 | G68: =(D68-C68*$B$5)*$B$15*F68-B68*$B$28-I68*B68*$B$9*F68 -> -144.05102 | H68: =(D68-C68*$B$5)*$C$15*F68-B68*($C$9/$B$9)*$B$28-I68*B68*$C$9*F68 -> -259.41978 | I68: =$B$16 -> 0 | J68: =D68*$B$15-C68*$B$5*$B$15-B68*$B$9/$B$18 -> -4.6604078 | K68: =IF($B$18<$B$7,"n/a",G68-$B$17*MAX(0,J68)*F68) -> -144.05102 | L68: =D68*$C$15-C68*$B$5*$C$15-B68*$C$9/$C$18 -> -11.758386 | M68: =IF($C$18<$C$7,"n/a",H68-$B$17*MAX(0,L68)*F68) -> -259.41978 | N68: Base
A69: Construction cost +5% | B69: 1.05 | C69: 1 | D69: 1 | E69: 0 | F69: =SUMPRODUCT($B$41:$B$63*($A$41:$A$63>=$B$8+E69)*($A$41:$A$63<$B$8+E69+$B$7)) -> 9.0908772 | G69: =(D69-C69*$B$5)*$B$15*F69-B69*$B$28-I69*B69*$B$9*F69 -> -153.68064 | H69: =(D69-C69*$B$5)*$C$15*F69-B69*($C$9/$B$9)*$B$28-I69*B69*$C$9*F69 -> -273.86422 | I69: =$B$16 -> 0 | J69: =D69*$B$15-C69*$B$5*$B$15-B69*$B$9/$B$18 -> -5.1604078 | K69: =IF($B$18<$B$7,"n/a",G69-$B$17*MAX(0,J69)*F69) -> -153.68064 | L69: =D69*$C$15-C69*$B$5*$C$15-B69*$C$9/$C$18 -> -12.508386 | M69: =IF($C$18<$C$7,"n/a",H69-$B$17*MAX(0,L69)*F69) -> -273.86422 | N69: Construction cost +5%
A70: Construction cost -5% | B70: 0.95 | C70: 1 | D70: 1 | E70: 0 | F70: =SUMPRODUCT($B$41:$B$63*($A$41:$A$63>=$B$8+E70)*($A$41:$A$63<$B$8+E70+$B$7)) -> 9.0908772 | G70: =(D70-C70*$B$5)*$B$15*F70-B70*$B$28-I70*B70*$B$9*F70 -> -134.42139 | H70: =(D70-C70*$B$5)*$C$15*F70-B70*($C$9/$B$9)*$B$28-I70*B70*$C$9*F70 -> -244.97533 | I70: =$B$16 -> 0 | J70: =D70*$B$15-C70*$B$5*$B$15-B70*$B$9/$B$18 -> -4.1604078 | K70: =IF($B$18<$B$7,"n/a",G70-$B$17*MAX(0,J70)*F70) -> -134.42139 | L70: =D70*$C$15-C70*$B$5*$C$15-B70*$C$9/$C$18 -> -11.008386 | M70: =IF($C$18<$C$7,"n/a",H70-$B$17*MAX(0,L70)*F70) -> -244.97533 | N70: Construction cost -5%
A71: Construction cost +10% | B71: 1.1 | C71: 1 | D71: 1 | E71: 0 | F71: =SUMPRODUCT($B$41:$B$63*($A$41:$A$63>=$B$8+E71)*($A$41:$A$63<$B$8+E71+$B$7)) -> 9.0908772 | G71: =(D71-C71*$B$5)*$B$15*F71-B71*$B$28-I71*B71*$B$9*F71 -> -163.31027 | H71: =(D71-C71*$B$5)*$C$15*F71-B71*($C$9/$B$9)*$B$28-I71*B71*$C$9*F71 -> -288.30867 | I71: =$B$16 -> 0 | J71: =D71*$B$15-C71*$B$5*$B$15-B71*$B$9/$B$18 -> -5.6604078 | K71: =IF($B$18<$B$7,"n/a",G71-$B$17*MAX(0,J71)*F71) -> -163.31027 | L71: =D71*$C$15-C71*$B$5*$C$15-B71*$C$9/$C$18 -> -13.258386 | M71: =IF($C$18<$C$7,"n/a",H71-$B$17*MAX(0,L71)*F71) -> -288.30867 | N71: Construction cost +10%
A72: Construction cost -10% | B72: 0.9 | C72: 1 | D72: 1 | E72: 0 | F72: =SUMPRODUCT($B$41:$B$63*($A$41:$A$63>=$B$8+E72)*($A$41:$A$63<$B$8+E72+$B$7)) -> 9.0908772 | G72: =(D72-C72*$B$5)*$B$15*F72-B72*$B$28-I72*B72*$B$9*F72 -> -124.79176 | H72: =(D72-C72*$B$5)*$C$15*F72-B72*($C$9/$B$9)*$B$28-I72*B72*$C$9*F72 -> -230.53089 | I72: =$B$16 -> 0 | J72: =D72*$B$15-C72*$B$5*$B$15-B72*$B$9/$B$18 -> -3.6604078 | K72: =IF($B$18<$B$7,"n/a",G72-$B$17*MAX(0,J72)*F72) -> -124.79176 | L72: =D72*$C$15-C72*$B$5*$C$15-B72*$C$9/$C$18 -> -10.258386 | M72: =IF($C$18<$C$7,"n/a",H72-$B$17*MAX(0,L72)*F72) -> -230.53089 | N72: Construction cost -10%
A73: Construction cost +20% | B73: 1.2 | C73: 1 | D73: 1 | E73: 0 | F73: =SUMPRODUCT($B$41:$B$63*($A$41:$A$63>=$B$8+E73)*($A$41:$A$63<$B$8+E73+$B$7)) -> 9.0908772 | G73: =(D73-C73*$B$5)*$B$15*F73-B73*$B$28-I73*B73*$B$9*F73 -> -182.56953 | H73: =(D73-C73*$B$5)*$C$15*F73-B73*($C$9/$B$9)*$B$28-I73*B73*$C$9*F73 -> -317.19756 | I73: =$B$16 -> 0 | J73: =D73*$B$15-C73*$B$5*$B$15-B73*$B$9/$B$18 -> -6.6604078 | K73: =IF($B$18<$B$7,"n/a",G73-$B$17*MAX(0,J73)*F73) -> -182.56953 | L73: =D73*$C$15-C73*$B$5*$C$15-B73*$C$9/$C$18 -> -14.758386 | M73: =IF($C$18<$C$7,"n/a",H73-$B$17*MAX(0,L73)*F73) -> -317.19756 | N73: Construction cost +20%
A74: Construction cost -20% | B74: 0.8 | C74: 1 | D74: 1 | E74: 0 | F74: =SUMPRODUCT($B$41:$B$63*($A$41:$A$63>=$B$8+E74)*($A$41:$A$63<$B$8+E74+$B$7)) -> 9.0908772 | G74: =(D74-C74*$B$5)*$B$15*F74-B74*$B$28-I74*B74*$B$9*F74 -> -105.5325 | H74: =(D74-C74*$B$5)*$C$15*F74-B74*($C$9/$B$9)*$B$28-I74*B74*$C$9*F74 -> -201.642 | I74: =$B$16 -> 0 | J74: =D74*$B$15-C74*$B$5*$B$15-B74*$B$9/$B$18 -> -2.6604078 | K74: =IF($B$18<$B$7,"n/a",G74-$B$17*MAX(0,J74)*F74) -> -105.5325 | L74: =D74*$C$15-C74*$B$5*$C$15-B74*$C$9/$C$18 -> -8.7583864 | M74: =IF($C$18<$C$7,"n/a",H74-$B$17*MAX(0,L74)*F74) -> -201.642 | N74: Construction cost -20%
A75: Operating cost +5% | B75: 1 | C75: 1.05 | D75: 1 | E75: 0 | F75: =SUMPRODUCT($B$41:$B$63*($A$41:$A$63>=$B$8+E75)*($A$41:$A$63<$B$8+E75+$B$7)) -> 9.0908772 | G75: =(D75-C75*$B$5)*$B$15*F75-B75*$B$28-I75*B75*$B$9*F75 -> -152.2328 | H75: =(D75-C75*$B$5)*$C$15*F75-B75*($C$9/$B$9)*$B$28-I75*B75*$C$9*F75 -> -264.38686 | I75: =$B$16 -> 0 | J75: =D75*$B$15-C75*$B$5*$B$15-B75*$B$9/$B$18 -> -5.5604069 | K75: =IF($B$18<$B$7,"n/a",G75-$B$17*MAX(0,J75)*F75) -> -152.2328 | L75: =D75*$C$15-C75*$B$5*$C$15-B75*$C$9/$C$18 -> -12.304767 | M75: =IF($C$18<$C$7,"n/a",H75-$B$17*MAX(0,L75)*F75) -> -264.38686 | N75: Operating cost +5%
A76: Operating cost -5% | B76: 1 | C76: 0.95 | D76: 1 | E76: 0 | F76: =SUMPRODUCT($B$41:$B$63*($A$41:$A$63>=$B$8+E76)*($A$41:$A$63<$B$8+E76+$B$7)) -> 9.0908772 | G76: =(D76-C76*$B$5)*$B$15*F76-B76*$B$28-I76*B76*$B$9*F76 -> -135.86923 | H76: =(D76-C76*$B$5)*$C$15*F76-B76*($C$9/$B$9)*$B$28-I76*B76*$C$9*F76 -> -254.4527 | I76: =$B$16 -> 0 | J76: =D76*$B$15-C76*$B$5*$B$15-B76*$B$9/$B$18 -> -3.7604087 | K76: =IF($B$18<$B$7,"n/a",G76-$B$17*MAX(0,J76)*F76) -> -135.86923 | L76: =D76*$C$15-C76*$B$5*$C$15-B76*$C$9/$C$18 -> -11.212006 | M76: =IF($C$18<$C$7,"n/a",H76-$B$17*MAX(0,L76)*F76) -> -254.4527 | N76: Operating cost -5%
A77: Operating cost +10% | B77: 1 | C77: 1.1 | D77: 1 | E77: 0 | F77: =SUMPRODUCT($B$41:$B$63*($A$41:$A$63>=$B$8+E77)*($A$41:$A$63<$B$8+E77+$B$7)) -> 9.0908772 | G77: =(D77-C77*$B$5)*$B$15*F77-B77*$B$28-I77*B77*$B$9*F77 -> -160.41458 | H77: =(D77-C77*$B$5)*$C$15*F77-B77*($C$9/$B$9)*$B$28-I77*B77*$C$9*F77 -> -269.35394 | I77: =$B$16 -> 0 | J77: =D77*$B$15-C77*$B$5*$B$15-B77*$B$9/$B$18 -> -6.4604061 | K77: =IF($B$18<$B$7,"n/a",G77-$B$17*MAX(0,J77)*F77) -> -160.41458 | L77: =D77*$C$15-C77*$B$5*$C$15-B77*$C$9/$C$18 -> -12.851148 | M77: =IF($C$18<$C$7,"n/a",H77-$B$17*MAX(0,L77)*F77) -> -269.35394 | N77: Operating cost +10%
A78: Operating cost -10% | B78: 1 | C78: 0.9 | D78: 1 | E78: 0 | F78: =SUMPRODUCT($B$41:$B$63*($A$41:$A$63>=$B$8+E78)*($A$41:$A$63<$B$8+E78+$B$7)) -> 9.0908772 | G78: =(D78-C78*$B$5)*$B$15*F78-B78*$B$28-I78*B78*$B$9*F78 -> -127.68745 | H78: =(D78-C78*$B$5)*$C$15*F78-B78*($C$9/$B$9)*$B$28-I78*B78*$C$9*F78 -> -249.48562 | I78: =$B$16 -> 0 | J78: =D78*$B$15-C78*$B$5*$B$15-B78*$B$9/$B$18 -> -2.8604095 | K78: =IF($B$18<$B$7,"n/a",G78-$B$17*MAX(0,J78)*F78) -> -127.68745 | L78: =D78*$C$15-C78*$B$5*$C$15-B78*$C$9/$C$18 -> -10.665625 | M78: =IF($C$18<$C$7,"n/a",H78-$B$17*MAX(0,L78)*F78) -> -249.48562 | N78: Operating cost -10%
A79: Operating cost +20% | B79: 1 | C79: 1.2 | D79: 1 | E79: 0 | F79: =SUMPRODUCT($B$41:$B$63*($A$41:$A$63>=$B$8+E79)*($A$41:$A$63<$B$8+E79+$B$7)) -> 9.0908772 | G79: =(D79-C79*$B$5)*$B$15*F79-B79*$B$28-I79*B79*$B$9*F79 -> -176.77814 | H79: =(D79-C79*$B$5)*$C$15*F79-B79*($C$9/$B$9)*$B$28-I79*B79*$C$9*F79 -> -279.28809 | I79: =$B$16 -> 0 | J79: =D79*$B$15-C79*$B$5*$B$15-B79*$B$9/$B$18 -> -8.2604043 | K79: =IF($B$18<$B$7,"n/a",G79-$B$17*MAX(0,J79)*F79) -> -176.77814 | L79: =D79*$C$15-C79*$B$5*$C$15-B79*$C$9/$C$18 -> -13.943909 | M79: =IF($C$18<$C$7,"n/a",H79-$B$17*MAX(0,L79)*F79) -> -279.28809 | N79: Operating cost +20%
... A93: One-year opening delay | B93: 1 | C93: 1 | D93: 1 | E93: 1 | F93: =SUMPRODUCT($B$41:$B$63*($A$41:$A$63>=$B$8+E93)*($A$41:$A$63<$B$8+E93+$B$7)) -> 8.4174789 | G93: =(D93-C93*$B$5)*$B$15*F93-B93*$B$28-I93*B93*$B$9*F93 -> -147.64669 | H93: =(D93-C93*$B$5)*$C$15*F93-B93*($C$9/$B$9)*$B$28-I93*B93*$C$9*F93 -> -261.60267 | I93: =$B$16 -> 0 | J93: =D93*$B$15-C93*$B$5*$B$15-B93*$B$9/$B$18 -> -4.6604078 | K93: =IF($B$18<$B$7,"n/a",G93-$B$17*MAX(0,J93)*F93) -> -147.64669 | L93: =D93*$C$15-C93*$B$5*$C$15-B93*$C$9/$C$18 -> -11.758386 | M93: =IF($C$18<$C$7,"n/a",H93-$B$17*MAX(0,L93)*F93) -> -261.60267 | N93: One-year opening delay
A94: Replacement at HK depreciation share | B94: 1 | C94: 1 | D94: 1 | E94: 0 | F94: =SUMPRODUCT($B$41:$B$63*($A$41:$A$63>=$B$8+E94)*($A$41:$A$63<$B$8+E94+$B$7)) -> 9.0908772 | G94: =(D94-C94*$B$5)*$B$15*F94-B94*$B$28-I94*B94*$B$9*F94 -> -287.85648 | H94: =(D94-C94*$B$5)*$C$15*F94-B94*($C$9/$B$9)*$B$28-I94*B94*$C$9*F94 -> -475.12797 | I94: =Inputs!$C$166 -> 0.079093281 | J94: =D94*$B$15-C94*$B$5*$B$15-B94*$B$9/$B$18 -> -4.6604078 | K94: =IF($B$18<$B$7,"n/a",G94-$B$17*MAX(0,J94)*F94) -> -287.85648 | L94: =D94*$C$15-C94*$B$5*$C$15-B94*$C$9/$C$18 -> -11.758386 | M94: =IF($C$18<$C$7,"n/a",H94-$B$17*MAX(0,L94)*F94) -> -475.12797 | N94: Replacement at HK depreciation share
A101: Scenarios (NPV before tax, THB bn)
A102: Scenario | B102: WACC | C102: Operating life (years) | D102: On-site income (1 = yes) | E102: Replacement share | F102: Revenue (THB bn a year) | G102: Annuity factor | H102: Capital present value | I102: NPV before tax (THB bn)
A103: Park-only, ticket and on-site revenue | B103: =B6 -> 0.08 | C103: =B7 -> 20 | D103: =$B$19 -> 1 | E103: =B16 -> 0 | F103: =$B$14*$B$13/1000+D103*$B$14*Inputs!$D$148/1000 -> 23.339575 | G103: =(1+B103)^(-$B$8)*(1-(1+B103)^(-C103))/(1-1/(1+B103)) -> 9.0908772 | H103: =($B$9/$B$8)*(1-(1+B103)^(-$B$8))/(1-1/(1+B103)) -> 192.59259 | I103: =(F103*(1-$B$5)-E103*$B$9)*G103-H103 -> -144.05102
A104: Ticket revenue only | B104: =B6 -> 0.08 | C104: =B7 -> 20 | D104: 0 | E104: =B16 -> 0 | F104: =$B$14*$B$13/1000+D104*$B$14*Inputs!$D$148/1000 -> 14.169225 | G104: =(1+B104)^(-$B$8)*(1-(1+B104)^(-C104))/(1-1/(1+B104)) -> 9.0908772 | H104: =($B$9/$B$8)*(1-(1+B104)^(-$B$8))/(1-1/(1+B104)) -> 192.59259 | I104: =(F104*(1-$B$5)-E104*$B$9)*G104-H104 -> -163.12348
A105: Operating life 30 years | B105: =B6 -> 0.08 | C105: 30 | D105: =$B$19 -> 1 | E105: =B16 -> 0 | F105: =$B$14*$B$13/1000+D105*$B$14*Inputs!$D$148/1000 -> 23.339575 | G105: =(1+B105)^(-$B$8)*(1-(1+B105)^(-C105))/(1-1/(1+B105)) -> 10.423873 | H105: =($B$9/$B$8)*(1-(1+B105)^(-$B$8))/(1-1/(1+B105)) -> 192.59259 | I105: =(F105*(1-$B$5)-E105*$B$9)*G105-H105 -> -136.93336
A106: Operating life 40 years | B106: =B6 -> 0.08 | C106: 40 | D106: =$B$19 -> 1 | E106: =B16 -> 0 | F106: =$B$14*$B$13/1000+D106*$B$14*Inputs!$D$148/1000 -> 23.339575 | G106: =(1+B106)^(-$B$8)*(1-(1+B106)^(-C106))/(1-1/(1+B106)) -> 11.041309 | H106: =($B$9/$B$8)*(1-(1+B106)^(-$B$8))/(1-1/(1+B106)) -> 192.59259 | I106: =(F106*(1-$B$5)-E106*$B$9)*G106-H106 -> -133.63651
A107: WACC 6% | B107: 0.06 | C107: =B7 -> 20 | D107: =$B$19 -> 1 | E107: =B16 -> 0 | F107: =$B$14*$B$13/1000+D107*$B$14*Inputs!$D$148/1000 -> 23.339575 | G107: =(1+B107)^(-$B$8)*(1-(1+B107)^(-C107))/(1-1/(1+B107)) -> 10.82068 | H107: =($B$9/$B$8)*(1-(1+B107)^(-$B$8))/(1-1/(1+B107)) -> 194.33962 | I107: =(F107*(1-$B$5)-E107*$B$9)*G107-H107 -> -136.5616
A108: WACC 7% | B108: 0.07 | C108: =B7 -> 20 | D108: =$B$19 -> 1 | E108: =B16 -> 0 | F108: =$B$14*$B$13/1000+D108*$B$14*Inputs!$D$148/1000 -> 23.339575 | G108: =(1+B108)^(-$B$8)*(1-(1+B108)^(-C108))/(1-1/(1+B108)) -> 9.9009479 | H108: =($B$9/$B$8)*(1-(1+B108)^(-$B$8))/(1-1/(1+B108)) -> 193.45794 | I108: =(F108*(1-$B$5)-E108*$B$9)*G108-H108 -> -140.59092
A109: WACC 10% | B109: 0.1 | C109: =B7 -> 20 | D109: =$B$19 -> 1 | E109: =B16 -> 0 | F109: =$B$14*$B$13/1000+D109*$B$14*Inputs!$D$148/1000 -> 23.339575 | G109: =(1+B109)^(-$B$8)*(1-(1+B109)^(-C109))/(1-1/(1+B109)) -> 7.7396034 | H109: =($B$9/$B$8)*(1-(1+B109)^(-$B$8))/(1-1/(1+B109)) -> 190.90909 | I109: =(F109*(1-$B$5)-E109*$B$9)*G109-H109 -> -149.58276
A110: Replacement at Hong Kong depreciation share | B110: =B6 -> 0.08 | C110: =B7 -> 20 | D110: =$B$19 -> 1 | E110: =Inputs!$C$166 -> 0.079093281 | F110: =$B$14*$B$13/1000+D110*$B$14*Inputs!$D$148/1000 -> 23.339575 | G110: =(1+B110)^(-$B$8)*(1-(1+B110)^(-C110))/(1-1/(1+B110)) -> 9.0908772 | H110: =($B$9/$B$8)*(1-(1+B110)^(-$B$8))/(1-1/(1+B110)) -> 192.59259 | I110: =(F110*(1-$B$5)-E110*$B$9)*G110-H110 -> -287.85648
A111: Operating life 30 years, replacement at HK share | B111: =B6 -> 0.08 | C111: 30 | D111: =$B$19 -> 1 | E111: =Inputs!$C$166 -> 0.079093281 | F111: =$B$14*$B$13/1000+D111*$B$14*Inputs!$D$148/1000 -> 23.339575 | G111: =(1+B111)^(-$B$8)*(1-(1+B111)^(-C111))/(1-1/(1+B111)) -> 10.423873 | H111: =($B$9/$B$8)*(1-(1+B111)^(-$B$8))/(1-1/(1+B111)) -> 192.59259 | I111: =(F111*(1-$B$5)-E111*$B$9)*G111-H111 -> -301.82503
A112: Ticket revenue only, replacement at HK share | B112: =B6 -> 0.08 | C112: =B7 -> 20 | D112: 0 | E112: =Inputs!$C$166 -> 0.079093281 | F112: =$B$14*$B$13/1000+D112*$B$14*Inputs!$D$148/1000 -> 14.169225 | G112: =(1+B112)^(-$B$8)*(1-(1+B112)^(-C112))/(1-1/(1+B112)) -> 9.0908772 | H112: =($B$9/$B$8)*(1-(1+B112)^(-$B$8))/(1-1/(1+B112)) -> 192.59259 | I112: =(F112*(1-$B$5)-E112*$B$9)*G112-H112 -> -306.92894
A113: Ticket revenue only, life 30 years, replacement at HK share | B113: =B6 -> 0.08 | C113: 30 | D113: 0 | E113: =Inputs!$C$166 -> 0.079093281 | F113: =$B$14*$B$13/1000+D113*$B$14*Inputs!$D$148/1000 -> 14.169225 | G113: =(1+B113)^(-$B$8)*(1-(1+B113)^(-C113))/(1-1/(1+B113)) -> 10.423873 | H113: =($B$9/$B$8)*(1-(1+B113)^(-$B$8))/(1-1/(1+B113)) -> 192.59259 | I113: =(F113*(1-$B$5)-E113*$B$9)*G113-H113 -> -323.69409
A118: Two-way sensitivity: NPV before tax (THB bn), capital cost by cash operating cost share
A119: Capital cost (THB bn) / cost share | B119: 0.7 | C119: =B5 -> 0.77122153 | D119: =Inputs!$C$151 -> 0.9383
A120: 150 | B120: =$B$15*(1-B$119)*$B$27-$A120*($B$28/$B$9)-$B$16*$A120*$B$27 -> -80.791281 | C120: =$B$15*(1-C$119)*$B$27-$A120*($B$28/$B$9)-$B$16*$A120*$B$27 -> -95.902867 | D120: =$B$15*(1-D$119)*$B$27-$A120*($B$28/$B$9)-$B$16*$A120*$B$27 -> -131.35311
A121: 200 | B121: =$B$15*(1-B$119)*$B$27-$A121*($B$28/$B$9)-$B$16*$A121*$B$27 -> -128.93943 | C121: =$B$15*(1-C$119)*$B$27-$A121*($B$28/$B$9)-$B$16*$A121*$B$27 -> -144.05102 | D121: =$B$15*(1-D$119)*$B$27-$A121*($B$28/$B$9)-$B$16*$A121*$B$27 -> -179.50126
A122: 250 | B122: =$B$15*(1-B$119)*$B$27-$A122*($B$28/$B$9)-$B$16*$A122*$B$27 -> -177.08758 | C122: =$B$15*(1-C$119)*$B$27-$A122*($B$28/$B$9)-$B$16*$A122*$B$27 -> -192.19916 | D122: =$B$15*(1-D$119)*$B$27-$A122*($B$28/$B$9)-$B$16*$A122*$B$27 -> -227.64941
A123: 300 | B123: =$B$15*(1-B$119)*$B$27-$A123*($B$28/$B$9)-$B$16*$A123*$B$27 -> -225.23573 | C123: =$B$15*(1-C$119)*$B$27-$A123*($B$28/$B$9)-$B$16*$A123*$B$27 -> -240.34731 | D123: =$B$15*(1-D$119)*$B$27-$A123*($B$28/$B$9)-$B$16*$A123*$B$27 -> -275.79755
A126: Attendance benchmarks (million visits a year)
A127: Park | B127: Attendance (million) | C127: Year | D127: Source
A128: Magic Kingdom (Walt Disney World) | B128: 17.8 | C128: 2024 | D128: TEA/AECOM ranking, reported by Disney Food Blog, 23 October 2025: https://disneyfoodblog.com/2025/10/23/magic-kingdom-is-the-1-most-visited-theme-park-in-the-world-but-the-rest-of-the-list-may-surprise-you
A129: Disneyland Park (California) | B129: 17.3 | C129: 2024 | D129: TEA/AECOM ranking, summarised by BGT Safari, 11 November 2025: https://bgtsafari.com/2025/11/11/the-tea-rankings-are-out-of-for-the-top-25-theme-parks-worldwide-and-almost-half-are-in-asia/
A130: Hong Kong Disneyland | B130: =Inputs!$C$83 -> 7.5 | C130: FY2025 | D130: Hong Kong Disneyland press release, 28 April 2026: https://news.hongkongdisneyland.com/en/press/2026-04-28/
A131: Shanghai Disneyland (approximate) | B131: 14 | C131: 2023 | D131: TEA/AECOM 2023 theme index (approximate)
A132: Tokyo Disney Resort (two parks) | B132: No verified figure | D132: No external source located
A134: Primary break-even attendance (million visits a year) | B134: =B25 -> 43.14715
A135: Multiple of Magic Kingdom attendance | B135: =B25/B128 -> 2.4239972

Sheet Charts
A1: Park-only operator appraisal: charts
